{
    "playlist_id": "PLxJlatU9FOa7TcXRo_RM-xvhtruGOdBqj",
    "playlist_title": "Slugterra All Episodes in Hindi",
    "playlist_published_at": "2021-02-11T17:30:26Z",
    "playlist_item_count": 172,
    "channel_name": "SR RECAPS",
    "videos": [
        {
            "video_id": "2jAINRqn9EA",
            "title": "\u0938\u094d\u0932\u0917\u091f\u0947\u0930\u093e | \u0939\u092e\u093e\u0930\u0947 \u0915\u0926\u092e\u094b\u0902 \u0915\u0947 \u0928\u0940\u091a\u0947 \u0915\u0940 \u0926\u0941\u0928\u093f\u092f\u093e \u092d\u093e\u0917 1 | \u0938\u0940\u091c\u093c\u0928 1 \u090f\u092a\u093f\u0938\u094b\u0921 1",
            "likes": "126788",
            "views": "12490435",
            "thumbnail": "https://i.ytimg.com/vi/2jAINRqn9EA/mqdefault.jpg"
        },
        {
            "video_id": "Hpa2DJnfXdA",
            "title": "\u0938\u094d\u0932\u0917\u091f\u0947\u0930\u093e | \u0939\u092e\u093e\u0930\u0947 \u0915\u0926\u092e\u094b\u0902 \u0915\u0947 \u0928\u0940\u091a\u0947 \u0915\u0940 \u0926\u0941\u0928\u093f\u092f\u093e \u092d\u093e\u0917 2 | \u0938\u0940\u091c\u093c\u0928 1 \u090f\u092a\u093f\u0938\u094b\u0921 2",
            "likes": "76200",
            "views": "6716751",
            "thumbnail": "https://i.ytimg.com/vi/Hpa2DJnfXdA/mqdefault.jpg"
        },
        {
            "video_id": "m9Rd_daRrJw",
            "title": "\u0938\u094d\u0932\u0917\u091f\u0947\u0930\u093e | \u0938\u094c\u0926\u093e | \u0938\u0940\u091c\u093c\u0928 1 \u090f\u092a\u093f\u0938\u094b\u0921 3",
            "likes": "49656",
            "views": "4422701",
            "thumbnail": "https://i.ytimg.com/vi/m9Rd_daRrJw/mqdefault.jpg"
        },
        {
            "video_id": "KbSem-xeYa4",
            "title": "\u0938\u094d\u0932\u0917\u091f\u0947\u0930\u093e | \u0938\u094d\u0932\u0917 \u0906\u0909\u091f | \u0938\u0940\u091c\u093c\u0928 1 \u090f\u092a\u093f\u0938\u094b\u0921 4",
            "likes": "56164",
            "views": "5619055",
            "thumbnail": "https://i.ytimg.com/vi/KbSem-xeYa4/mqdefault.jpg"
        },
        {
            "video_id": "t2M9LanStgo",
            "title": "\u0938\u094d\u0932\u0917\u091f\u0947\u0930\u093e | \u0938\u094d\u0932\u0917 \u0915\u0940 \u0915\u094d\u0932\u092c | \u0938\u0940\u091c\u093c\u0928 1 \u090f\u092a\u093f\u0938\u094b\u0921 5",
            "likes": "38558",
            "views": "3435998",
            "thumbnail": "https://i.ytimg.com/vi/t2M9LanStgo/mqdefault.jpg"
        },
        {
            "video_id": "i_mMetwiVU0",
            "title": "\u0938\u094d\u0932\u0917\u091f\u0947\u0930\u093e | \u0938\u094d\u0932\u0917 \u0926\u094c\u095c \u092a\u094d\u0930\u0924\u093f\u092f\u094b\u0917\u093f\u0924\u093e | \u0938\u0940\u091c\u093c\u0928 1 \u090f\u092a\u093f\u0938\u094b\u0921 6",
            "likes": "47079",
            "views": "4605622",
            "thumbnail": "https://i.ytimg.com/vi/i_mMetwiVU0/mqdefault.jpg"
        },
        {
            "video_id": "xq_5Sboe2vY",
            "title": "\u0938\u094d\u0932\u0917\u091f\u0947\u0930\u093e | \u092e\u0947\u0915\u093e \u0935\u093f\u0926\u094d\u0930\u094b\u0939 | \u0938\u0940\u091c\u093c\u0928 1 \u090f\u092a\u093f\u0938\u094b\u0921 7",
            "likes": "43907",
            "views": "4394429",
            "thumbnail": "https://i.ytimg.com/vi/xq_5Sboe2vY/mqdefault.jpg"
        },
        {
            "video_id": "S4MNWCuPlz4",
            "title": "\u0938\u094d\u0932\u0917\u091f\u0947\u0930\u093e | \u0921\u0947\u0921\u0935\u0940\u0921 | \u0938\u0940\u091c\u093c\u0928 1 \u090f\u092a\u093f\u0938\u094b\u0921 8",
            "likes": "36061",
            "views": "3567421",
            "thumbnail": "https://i.ytimg.com/vi/S4MNWCuPlz4/mqdefault.jpg"
        },
        {
            "video_id": "58HQNTOO76U",
            "title": "\u0938\u094d\u0932\u0917\u091f\u0947\u0930\u093e | \u0930\u094c\u0936\u0928\u0940 \u0914\u0930 \u0905\u0901\u0927\u0947\u0930\u093e | \u0938\u0940\u091c\u093c\u0928 1 \u090f\u092a\u093f\u0938\u094b\u0921 9",
            "likes": "37750",
            "views": "3922090",
            "thumbnail": "https://i.ytimg.com/vi/58HQNTOO76U/mqdefault.jpg"
        },
        {
            "video_id": "1Nq3Vxim0CQ",
            "title": "\u0938\u094d\u0932\u0917\u091f\u0947\u0930\u093e | \u092e\u093e\u0930\u093f\u092f\u094b \u092c\u094d\u0930\u0935\u093e\u0921\u094b | \u0938\u0940\u091c\u093c\u0928 1 \u090f\u092a\u093f\u0938\u094b\u0921 10",
            "likes": "37355",
            "views": "3240848",
            "thumbnail": "https://i.ytimg.com/vi/1Nq3Vxim0CQ/mqdefault.jpg"
        },
        {
            "video_id": "xA6BqPe2uVA",
            "title": "\u0938\u094d\u0932\u0917\u091f\u0947\u0930\u093e | \u0932\u0941\u092a\u094d\u0924\u092a\u094d\u0930\u093e\u092f \u092a\u094d\u0930\u091c\u093e\u0924\u093f\u092f\u093e\u0902 | \u0938\u0940\u091c\u093c\u0928 1 \u090f\u092a\u093f\u0938\u094b\u0921 11",
            "likes": "32833",
            "views": "3254179",
            "thumbnail": "https://i.ytimg.com/vi/xA6BqPe2uVA/mqdefault.jpg"
        },
        {
            "video_id": "JDKMtm9ap8A",
            "title": "\u0938\u094d\u0932\u0917\u091f\u0947\u0930\u093e | \u092a\u094d\u0930\u0935\u093e\u0939 | \u0938\u0940\u091c\u093c\u0928 1 \u090f\u092a\u093f\u0938\u094b\u0921 12",
            "likes": "32409",
            "views": "3328306",
            "thumbnail": "https://i.ytimg.com/vi/JDKMtm9ap8A/mqdefault.jpg"
        },
        {
            "video_id": "lJ5qnUD03j8",
            "title": "\u0938\u094d\u0932\u0917\u091f\u0947\u0930\u093e | \u095b\u094b\u092e\u094d\u092c\u0940 \u0938\u094d\u0932\u0917 | \u0938\u0940\u091c\u093c\u0928 1 \u090f\u092a\u093f\u0938\u094b\u0921 13",
            "likes": "31477",
            "views": "2865842",
            "thumbnail": "https://i.ytimg.com/vi/lJ5qnUD03j8/mqdefault.jpg"
        },
        {
            "video_id": "kKl4WZIaVcg",
            "title": "\u0938\u094d\u0932\u0917\u091f\u0947\u0930\u093e |\u090f\u0915 \u0928\u092f\u093e \u0938\u093e\u0925\u0940 \u092d\u093e\u0917 1 | \u0938\u0940\u091c\u093c\u0928 1 \u090f\u092a\u093f\u0938\u094b\u0921 14",
            "likes": "28347",
            "views": "2623985",
            "thumbnail": "https://i.ytimg.com/vi/kKl4WZIaVcg/mqdefault.jpg"
        },
        {
            "video_id": "4JXSoq0bmu8",
            "title": "\u0938\u094d\u0932\u0917\u091f\u0947\u0930\u093e | \u090f\u0915 \u0928\u092f\u093e \u0938\u093e\u0925\u0940 \u092d\u093e\u0917 2 | \u0938\u0940\u091c\u093c\u0928 1 \u090f\u092a\u093f\u0938\u094b\u0921 15",
            "likes": "28795",
            "views": "2786334",
            "thumbnail": "https://i.ytimg.com/vi/4JXSoq0bmu8/mqdefault.jpg"
        },
        {
            "video_id": "NL6bUay_g50",
            "title": "\u0938\u094d\u0932\u0917\u091f\u0947\u0930\u093e | \u092c\u0930\u094d\u092b \u0915\u093e \u0916\u0947\u0932 | \u0938\u0940\u091c\u093c\u0928 1 \u090f\u092a\u093f\u0938\u094b\u0921 16",
            "likes": "27978",
            "views": "2986936",
            "thumbnail": "https://i.ytimg.com/vi/NL6bUay_g50/mqdefault.jpg"
        },
        {
            "video_id": "HRJa0gdxC-8",
            "title": "\u0938\u094d\u0932\u0917\u091f\u0947\u0930\u093e | \u0935\u093f\u0930\u093e\u0938\u0924 | \u0938\u0940\u091c\u093c\u0928 1 \u090f\u092a\u093f\u0938\u094b\u0921 17",
            "likes": "28128",
            "views": "2927612",
            "thumbnail": "https://i.ytimg.com/vi/HRJa0gdxC-8/mqdefault.jpg"
        },
        {
            "video_id": "lac65g_IfxI",
            "title": "\u0938\u094d\u0932\u0917\u091f\u0947\u0930\u093e | \u090f\u0915 \u0926\u0942\u0930\u0938\u094d\u0925 \u0924\u091f | \u0938\u0940\u091c\u093c\u0928 1 \u090f\u092a\u093f\u0938\u094b\u0921 18",
            "likes": "41147",
            "views": "3437236",
            "thumbnail": "https://i.ytimg.com/vi/lac65g_IfxI/mqdefault.jpg"
        },
        {
            "video_id": "ZOJMoi5BHIQ",
            "title": "\u0938\u094d\u0932\u0917\u091f\u0947\u0930\u093e | \u0938\u095e\u0930 \u0918\u0930 \u0924\u0915 | \u0938\u0940\u091c\u093c\u0928 1 \u090f\u092a\u093f\u0938\u094b\u0921 19",
            "likes": "26324",
            "views": "2980927",
            "thumbnail": "https://i.ytimg.com/vi/ZOJMoi5BHIQ/mqdefault.jpg"
        },
        {
            "video_id": "lqSlCuweIrU",
            "title": "\u0938\u094d\u0932\u0917\u091f\u0947\u0930\u093e | \u0930\u094b\u092c\u094b \u0938\u094d\u0932\u0917\u094d\u0938 | \u0938\u0940\u091c\u093c\u0928 1 \u090f\u092a\u093f\u0938\u094b\u0921 20",
            "likes": "34257",
            "views": "3545507",
            "thumbnail": "https://i.ytimg.com/vi/lqSlCuweIrU/mqdefault.jpg"
        },
        {
            "video_id": "V25S9Qhm5DI",
            "title": "\u0938\u094d\u0932\u0917\u091f\u0947\u0930\u093e | \u0905\u092a\u0930\u093e\u091c\u0947\u092f \u092f\u094b\u0926\u094d\u0927\u093e | \u0938\u0940\u091c\u093c\u0928 1 \u090f\u092a\u093f\u0938\u094b\u0921 21",
            "likes": "54337",
            "views": "6338054",
            "thumbnail": "https://i.ytimg.com/vi/V25S9Qhm5DI/mqdefault.jpg"
        },
        {
            "video_id": "vCN_68YE9Z8",
            "title": "\u0938\u094d\u0932\u0917\u091f\u0947\u0930\u093e | \u0917\u0939\u0930\u093e \u092a\u093e\u0928\u0940, \u0915\u093e\u0932\u093e \u092a\u093e\u0928\u0940 | \u0938\u0940\u091c\u093c\u0928 1 \u090f\u092a\u093f\u0938\u094b\u0921 22",
            "likes": "29678",
            "views": "3107413",
            "thumbnail": "https://i.ytimg.com/vi/vCN_68YE9Z8/mqdefault.jpg"
        },
        {
            "video_id": "bUjLsz4d7Aw",
            "title": "\u0938\u094d\u0932\u0917\u091f\u0947\u0930\u093e | \u091c\u0947\u0902\u091f\u0932\u092e\u0948\u0928 \u0914\u0930 \u091a\u094b\u0930 | \u0938\u0940\u091c\u093c\u0928 1 \u090f\u092a\u093f\u0938\u094b\u0921 23",
            "likes": "31056",
            "views": "3043202",
            "thumbnail": "https://i.ytimg.com/vi/bUjLsz4d7Aw/mqdefault.jpg"
        },
        {
            "video_id": "KiC8NiLoiZ8",
            "title": "\u0938\u094d\u0932\u0917\u091f\u0947\u0930\u093e | \u091a\u0915\u094d\u0930\u0935\u094d\u092f\u0942\u0939 | \u0938\u0940\u091c\u093c\u0928 1 \u090f\u092a\u093f\u0938\u094b\u0921 24",
            "likes": "33186",
            "views": "3125778",
            "thumbnail": "https://i.ytimg.com/vi/KiC8NiLoiZ8/mqdefault.jpg"
        },
        {
            "video_id": "CHJ3q7QjKK0",
            "title": "\u0938\u094d\u0932\u0917\u091f\u0947\u0930\u093e | \u092e\u0941\u0936\u094d\u0915\u093f\u0932 \u092d\u093e\u0917 | \u0938\u0940\u091c\u093c\u0928 1 \u090f\u092a\u093f\u0938\u094b\u0921 25",
            "likes": "37455",
            "views": "4037664",
            "thumbnail": "https://i.ytimg.com/vi/CHJ3q7QjKK0/mqdefault.jpg"
        },
        {
            "video_id": "j7TV1A52Qic",
            "title": "\u0938\u094d\u0932\u0917\u091f\u0947\u0930\u093e | \u0928\u0940\u091a\u0947 \u0915\u094d\u092f\u093e \u091b\u0941\u092a\u093e \u0939\u0948 | \u0938\u0940\u091c\u093c\u0928 1 \u090f\u092a\u093f\u0938\u094b\u0921 26",
            "likes": "67014",
            "views": "7410985",
            "thumbnail": "https://i.ytimg.com/vi/j7TV1A52Qic/mqdefault.jpg"
        },
        {
            "video_id": "_OKhT7hAfjY",
            "title": "Slugterra Episode 27(Part 1) in hindi #Slugterra #Hindi",
            "likes": "8963",
            "views": "896051",
            "thumbnail": "https://i.ytimg.com/vi/_OKhT7hAfjY/mqdefault.jpg"
        },
        {
            "video_id": "WQG2wg7nI60",
            "title": "Slugterra Episode 27(Part 2) in hindi #Slugterra #Hindi",
            "likes": "4797",
            "views": "597765",
            "thumbnail": "https://i.ytimg.com/vi/WQG2wg7nI60/mqdefault.jpg"
        },
        {
            "video_id": "gxOOVKVujbg",
            "title": "Slugterra Episode 27(Part 3) in hindi #Slugterra #Hindi",
            "likes": "5671",
            "views": "560451",
            "thumbnail": "https://i.ytimg.com/vi/gxOOVKVujbg/mqdefault.jpg"
        },
        {
            "video_id": "x5tg1BFJTFg",
            "title": "Slugterra Episode 27(Part 4) in hindi #Slugterra #Hindi",
            "likes": "3976",
            "views": "512758",
            "thumbnail": "https://i.ytimg.com/vi/x5tg1BFJTFg/mqdefault.jpg"
        },
        {
            "video_id": "4K8-nqLSD6c",
            "title": "Slugterra Episode 27(Part 5) in hindi #Slugterra #Hindi",
            "likes": "4113",
            "views": "526395",
            "thumbnail": "https://i.ytimg.com/vi/4K8-nqLSD6c/mqdefault.jpg"
        },
        {
            "video_id": "q9FDHNt5So4",
            "title": "Slugterra Episode 27(Part 6) in hindi #Slugterra #Hindi",
            "likes": "6082",
            "views": "685840",
            "thumbnail": "https://i.ytimg.com/vi/q9FDHNt5So4/mqdefault.jpg"
        },
        {
            "video_id": "491gsOM8PyI",
            "title": "Slugterra Episode 27(Part 7) in hindi #Slugterra #Hindi",
            "likes": "5136",
            "views": "569087",
            "thumbnail": "https://i.ytimg.com/vi/491gsOM8PyI/mqdefault.jpg"
        },
        {
            "video_id": "rsH-nMkh7hk",
            "title": "Slugterra Episode 28(Part 1) in hindi #Slugterra #Hindi",
            "likes": "5464",
            "views": "575621",
            "thumbnail": "https://i.ytimg.com/vi/rsH-nMkh7hk/mqdefault.jpg"
        },
        {
            "video_id": "fJO_ZmKw2No",
            "title": "Slugterra Episode 28(Part 2) in hindi #Slugterra #Hindi",
            "likes": "4124",
            "views": "434299",
            "thumbnail": "https://i.ytimg.com/vi/fJO_ZmKw2No/mqdefault.jpg"
        },
        {
            "video_id": "qITSLY3pmnI",
            "title": "Slugterra Episode 28(Part 3) in hindi #Slugterra #Hindi",
            "likes": "3058",
            "views": "427475",
            "thumbnail": "https://i.ytimg.com/vi/qITSLY3pmnI/mqdefault.jpg"
        },
        {
            "video_id": "zBZ7gzD0rrM",
            "title": "Slugterra Episode 28(Part 4) in hindi #Slugterra #Hindi",
            "likes": "3968",
            "views": "414306",
            "thumbnail": "https://i.ytimg.com/vi/zBZ7gzD0rrM/mqdefault.jpg"
        },
        {
            "video_id": "CB5NCNen7OA",
            "title": "Slugterra Episode 28(Part 5) in hindi #Slugterra #Hindi",
            "likes": "3656",
            "views": "403657",
            "thumbnail": "https://i.ytimg.com/vi/CB5NCNen7OA/mqdefault.jpg"
        },
        {
            "video_id": "rHHW1-ezvdY",
            "title": "Slugterra Episode 28(Part 6) in hindi #Slugterra #Hindi",
            "likes": "3891",
            "views": "394367",
            "thumbnail": "https://i.ytimg.com/vi/rHHW1-ezvdY/mqdefault.jpg"
        },
        {
            "video_id": "g_CbJnY0Ymo",
            "title": "Slugterra Episode 29(Part 1) in hindi #Slugterra #Hindi",
            "likes": "5147",
            "views": "532891",
            "thumbnail": "https://i.ytimg.com/vi/g_CbJnY0Ymo/mqdefault.jpg"
        },
        {
            "video_id": "WUz0plIZdTs",
            "title": "Slugterra Episode 29(Part 2) in hindi #Slugterra #Hindi",
            "likes": "3527",
            "views": "396932",
            "thumbnail": "https://i.ytimg.com/vi/WUz0plIZdTs/mqdefault.jpg"
        },
        {
            "video_id": "JfWi54-pt3c",
            "title": "Slugterra Episode 29(Part 3) in hindi #Slugterra #Hindi",
            "likes": "3531",
            "views": "378013",
            "thumbnail": "https://i.ytimg.com/vi/JfWi54-pt3c/mqdefault.jpg"
        },
        {
            "video_id": "j45arbdnLw0",
            "title": "Slugterra Episode 29(Part 4) in hindi #Slugterra #Hindi",
            "likes": "3026",
            "views": "363413",
            "thumbnail": "https://i.ytimg.com/vi/j45arbdnLw0/mqdefault.jpg"
        },
        {
            "video_id": "m5UTxmIaIg4",
            "title": "Slugterra Episode 29(Part 5) in hindi #Slugterra #Hindi",
            "likes": "3018",
            "views": "346473",
            "thumbnail": "https://i.ytimg.com/vi/m5UTxmIaIg4/mqdefault.jpg"
        },
        {
            "video_id": "4toVUf-LEWQ",
            "title": "Slugterra Episode 29(Part 6) in hindi #Slugterra #Hindi",
            "likes": "3403",
            "views": "354647",
            "thumbnail": "https://i.ytimg.com/vi/4toVUf-LEWQ/mqdefault.jpg"
        },
        {
            "video_id": "TJT2rFpD8Bw",
            "title": "Slugterra Episode 30(Part 1) in hindi #Slugterra #Hindi",
            "likes": "4844",
            "views": "459080",
            "thumbnail": "https://i.ytimg.com/vi/TJT2rFpD8Bw/mqdefault.jpg"
        },
        {
            "video_id": "FSLY2hcBktY",
            "title": "Slugterra Episode 30(Part 2) in hindi #Slugterra #Hindi",
            "likes": "2938",
            "views": "369905",
            "thumbnail": "https://i.ytimg.com/vi/FSLY2hcBktY/mqdefault.jpg"
        },
        {
            "video_id": "tsuuitf_OnM",
            "title": "Slugterra Episode 30(Part 3) in hindi #Slugterra #Hindi",
            "likes": "2729",
            "views": "360387",
            "thumbnail": "https://i.ytimg.com/vi/tsuuitf_OnM/mqdefault.jpg"
        },
        {
            "video_id": "SvepNe8OQfw",
            "title": "Slugterra Episode 30(Part 4) in hindi #Slugterra #Hindi",
            "likes": "2241",
            "views": "352894",
            "thumbnail": "https://i.ytimg.com/vi/SvepNe8OQfw/mqdefault.jpg"
        },
        {
            "video_id": "uYggYrjyAko",
            "title": "Slugterra Episode 30(Part 5) in hindi #Slugterra #Hindi",
            "likes": "2798",
            "views": "363535",
            "thumbnail": "https://i.ytimg.com/vi/uYggYrjyAko/mqdefault.jpg"
        },
        {
            "video_id": "bvfl47xfLEo",
            "title": "Slugterra Episode 30(Part 6) in hindi #Slugterra #Hindi",
            "likes": "3134",
            "views": "366705",
            "thumbnail": "https://i.ytimg.com/vi/bvfl47xfLEo/mqdefault.jpg"
        },
        {
            "video_id": "EJjyqpiSFPY",
            "title": "Slugterra Episode 31(Part 1) in hindi #Slugterra #Hindi",
            "likes": "4532",
            "views": "446749",
            "thumbnail": "https://i.ytimg.com/vi/EJjyqpiSFPY/mqdefault.jpg"
        },
        {
            "video_id": "iBpznsn1KMM",
            "title": "Slugterra Episode 31(Part 2) in hindi #Slugterra #Hindi",
            "likes": "3355",
            "views": "381904",
            "thumbnail": "https://i.ytimg.com/vi/iBpznsn1KMM/mqdefault.jpg"
        },
        {
            "video_id": "s1LW_WLuqi8",
            "title": "Slugterra Episode 31(Part 3) in hindi #Slugterra #Hindi",
            "likes": "2813",
            "views": "361352",
            "thumbnail": "https://i.ytimg.com/vi/s1LW_WLuqi8/mqdefault.jpg"
        },
        {
            "video_id": "Fy7J9SujviE",
            "title": "Slugterra Episode 31(Part 4) in hindi #Slugterra #Hindi",
            "likes": "2516",
            "views": "345142",
            "thumbnail": "https://i.ytimg.com/vi/Fy7J9SujviE/mqdefault.jpg"
        },
        {
            "video_id": "9c2qoB0P1uc",
            "title": "Slugterra Episode 31(Part 5) in hindi #Slugterra #Hindi",
            "likes": "2714",
            "views": "362351",
            "thumbnail": "https://i.ytimg.com/vi/9c2qoB0P1uc/mqdefault.jpg"
        },
        {
            "video_id": "aVD_5Dr0uxs",
            "title": "Slugterra Episode 31(Part 6) in hindi #Slugterra #Hindi",
            "likes": "3174",
            "views": "364797",
            "thumbnail": "https://i.ytimg.com/vi/aVD_5Dr0uxs/mqdefault.jpg"
        },
        {
            "video_id": "-q2dEgsZi6M",
            "title": "Slugterra Episode 32(Part 1) in hindi #Slugterra #Hindi",
            "likes": "4655",
            "views": "450807",
            "thumbnail": "https://i.ytimg.com/vi/-q2dEgsZi6M/mqdefault.jpg"
        },
        {
            "video_id": "3zLR2p3eEaU",
            "title": "Slugterra Episode 32(Part 2) in hindi #Slugterra #Hindi",
            "likes": "2962",
            "views": "364099",
            "thumbnail": "https://i.ytimg.com/vi/3zLR2p3eEaU/mqdefault.jpg"
        },
        {
            "video_id": "8bIFxtJbJzU",
            "title": "Slugterra Episode 32(Part 3) in hindi #Slugterra #Hindi",
            "likes": "2520",
            "views": "347633",
            "thumbnail": "https://i.ytimg.com/vi/8bIFxtJbJzU/mqdefault.jpg"
        },
        {
            "video_id": "ZHHFfglwwS4",
            "title": "Slugterra Episode 32(Part 4) in hindi #Slugterra #Hindi",
            "likes": "2276",
            "views": "344624",
            "thumbnail": "https://i.ytimg.com/vi/ZHHFfglwwS4/mqdefault.jpg"
        },
        {
            "video_id": "1P5PhYBA3r4",
            "title": "Slugterra Episode 32(Part 5) in hindi #Slugterra #Hindi",
            "likes": "2237",
            "views": "349205",
            "thumbnail": "https://i.ytimg.com/vi/1P5PhYBA3r4/mqdefault.jpg"
        },
        {
            "video_id": "_NSKgpxL0rg",
            "title": "Slugterra Episode 32(Part 6) in hindi #Slugterra #Hindi",
            "likes": "11045",
            "views": "1348452",
            "thumbnail": "https://i.ytimg.com/vi/_NSKgpxL0rg/mqdefault.jpg"
        },
        {
            "video_id": "yzwkr01Yqa4",
            "title": "Slugterra Episode 33(Part 1) in hindi #Slugterra #Hindi",
            "likes": "3978",
            "views": "445338",
            "thumbnail": "https://i.ytimg.com/vi/yzwkr01Yqa4/mqdefault.jpg"
        },
        {
            "video_id": "mmJWF0wj3C4",
            "title": "Slugterra Episode 33(Part 2) in hindi #Slugterra #Hindi",
            "likes": "3249",
            "views": "383913",
            "thumbnail": "https://i.ytimg.com/vi/mmJWF0wj3C4/mqdefault.jpg"
        },
        {
            "video_id": "0zBb3dQzVi0",
            "title": "Slugterra Episode 33(Part 3) in hindi #Slugterra #Hindi",
            "likes": "3013",
            "views": "374245",
            "thumbnail": "https://i.ytimg.com/vi/0zBb3dQzVi0/mqdefault.jpg"
        },
        {
            "video_id": "bDRvXfULUoU",
            "title": "Slugterra Episode 33(Part 4) in hindi #Slugterra #Hindi",
            "likes": "2918",
            "views": "374633",
            "thumbnail": "https://i.ytimg.com/vi/bDRvXfULUoU/mqdefault.jpg"
        },
        {
            "video_id": "Kx79AjP_W-4",
            "title": "Slugterra Episode 33(Part 5) in hindi #Slugterra #Hindi",
            "likes": "2807",
            "views": "366271",
            "thumbnail": "https://i.ytimg.com/vi/Kx79AjP_W-4/mqdefault.jpg"
        },
        {
            "video_id": "VGhmU_4kai4",
            "title": "Slugterra Episode 33(Part 6) in hindi #Slugterra #Hindi",
            "likes": "3576",
            "views": "389238",
            "thumbnail": "https://i.ytimg.com/vi/VGhmU_4kai4/mqdefault.jpg"
        },
        {
            "video_id": "wpCFSMasjHo",
            "title": "Slugterra Episode 34(Part 1) in hindi #Slugterra #Hindi",
            "likes": "4032",
            "views": "428268",
            "thumbnail": "https://i.ytimg.com/vi/wpCFSMasjHo/mqdefault.jpg"
        },
        {
            "video_id": "DDlyb_3p644",
            "title": "Slugterra Episode 34(Part 2) in hindi #Slugterra #Hindi",
            "likes": "3607",
            "views": "363420",
            "thumbnail": "https://i.ytimg.com/vi/DDlyb_3p644/mqdefault.jpg"
        },
        {
            "video_id": "UL0imwrzf_E",
            "title": "Slugterra Episode 34(Part 3) in hindi #Slugterra #Hindi",
            "likes": "2380",
            "views": "344960",
            "thumbnail": "https://i.ytimg.com/vi/UL0imwrzf_E/mqdefault.jpg"
        },
        {
            "video_id": "K0BtzpVWsVo",
            "title": "Slugterra Episode 34(Part 4) in hindi #Slugterra #Hindi",
            "likes": "3093",
            "views": "348372",
            "thumbnail": "https://i.ytimg.com/vi/K0BtzpVWsVo/mqdefault.jpg"
        },
        {
            "video_id": "jUb0xcNQyts",
            "title": "Slugterra Episode 34(Part 5) in hindi #Slugterra #Hindi",
            "likes": "2748",
            "views": "352970",
            "thumbnail": "https://i.ytimg.com/vi/jUb0xcNQyts/mqdefault.jpg"
        },
        {
            "video_id": "IDZKp8eLPxE",
            "title": "Slugterra Episode 34(Part 6) in hindi #Slugterra #Hindi",
            "likes": "2908",
            "views": "355951",
            "thumbnail": "https://i.ytimg.com/vi/IDZKp8eLPxE/mqdefault.jpg"
        },
        {
            "video_id": "Qia8qH6mffE",
            "title": "Slugterra Episode 35(Part 1) in hindi #Slugterra #Hindi",
            "likes": "5027",
            "views": "495026",
            "thumbnail": "https://i.ytimg.com/vi/Qia8qH6mffE/mqdefault.jpg"
        },
        {
            "video_id": "VZrPI4iYUq0",
            "title": "Slugterra Episode 35(Part 2) in hindi #Slugterra #Hindi",
            "likes": "3231",
            "views": "427976",
            "thumbnail": "https://i.ytimg.com/vi/VZrPI4iYUq0/mqdefault.jpg"
        },
        {
            "video_id": "yRMrS4WD8nw",
            "title": "Slugterra Episode 35(Part 3) in hindi #Slugterra #Hindi",
            "likes": "3217",
            "views": "402821",
            "thumbnail": "https://i.ytimg.com/vi/yRMrS4WD8nw/mqdefault.jpg"
        },
        {
            "video_id": "EmRXfIzxnvk",
            "title": "Slugterra Episode 35(Part 4) in hindi #Slugterra #Hindi",
            "likes": "2822",
            "views": "403576",
            "thumbnail": "https://i.ytimg.com/vi/EmRXfIzxnvk/mqdefault.jpg"
        },
        {
            "video_id": "au6JXHPx0-Y",
            "title": "Slugterra Episode 35(Part 5) in hindi #Slugterra #Hindi",
            "likes": "3167",
            "views": "423690",
            "thumbnail": "https://i.ytimg.com/vi/au6JXHPx0-Y/mqdefault.jpg"
        },
        {
            "video_id": "Nf1SCWZyS48",
            "title": "Slugterra Episode 35(Part 6) in hindi #Slugterra #Hindi",
            "likes": "3398",
            "views": "422974",
            "thumbnail": "https://i.ytimg.com/vi/Nf1SCWZyS48/mqdefault.jpg"
        },
        {
            "video_id": "AOqsCwwvuw4",
            "title": "Slugterra Episode 36(Part 1) in hindi #Slugterra #Hindi",
            "likes": "4215",
            "views": "437026",
            "thumbnail": "https://i.ytimg.com/vi/AOqsCwwvuw4/mqdefault.jpg"
        },
        {
            "video_id": "LTQVmSh2AKk",
            "title": "Slugterra Episode 36(Part 2) in hindi #Slugterra #Hindi",
            "likes": "3960",
            "views": "397418",
            "thumbnail": "https://i.ytimg.com/vi/LTQVmSh2AKk/mqdefault.jpg"
        },
        {
            "video_id": "z0_xUTH5XCc",
            "title": "Slugterra Episode 36(Part 3) in hindi #Slugterra #Hindi",
            "likes": "3634",
            "views": "383454",
            "thumbnail": "https://i.ytimg.com/vi/z0_xUTH5XCc/mqdefault.jpg"
        },
        {
            "video_id": "IIlG_N6N1zA",
            "title": "Slugterra Episode 36(Part 4) in hindi #Slugterra #Hindi",
            "likes": "3342",
            "views": "382429",
            "thumbnail": "https://i.ytimg.com/vi/IIlG_N6N1zA/mqdefault.jpg"
        },
        {
            "video_id": "VmDKy7LN0Nk",
            "title": "Slugterra Episode 36(Part 5) in hindi #Slugterra #Hindi",
            "likes": "4191",
            "views": "489753",
            "thumbnail": "https://i.ytimg.com/vi/VmDKy7LN0Nk/mqdefault.jpg"
        },
        {
            "video_id": "ObeC-kMZw1E",
            "title": "Slugterra Episode 36(Part 6) in hindi #Slugterra #Hindi",
            "likes": "4641",
            "views": "425274",
            "thumbnail": "https://i.ytimg.com/vi/ObeC-kMZw1E/mqdefault.jpg"
        },
        {
            "video_id": "IdeEC9vcGEM",
            "title": "Slugterra Episode 37(Part 1) in hindi #Slugterra #Hindi",
            "likes": "3671",
            "views": "442038",
            "thumbnail": "https://i.ytimg.com/vi/IdeEC9vcGEM/mqdefault.jpg"
        },
        {
            "video_id": "xl0nyJpEXzI",
            "title": "Slugterra Episode 37(Part 2) in hindi #Slugterra #Hindi",
            "likes": "5513",
            "views": "700074",
            "thumbnail": "https://i.ytimg.com/vi/xl0nyJpEXzI/mqdefault.jpg"
        },
        {
            "video_id": "hPYP0_Q9MeI",
            "title": "Slugterra Episode 37(Part 3) in hindi #Slugterra #Hindi",
            "likes": "3284",
            "views": "530136",
            "thumbnail": "https://i.ytimg.com/vi/hPYP0_Q9MeI/mqdefault.jpg"
        },
        {
            "video_id": "slOjHfkAtI4",
            "title": "Slugterra Episode 37(Part 4) in hindi #Slugterra #Hindi",
            "likes": "3496",
            "views": "435490",
            "thumbnail": "https://i.ytimg.com/vi/slOjHfkAtI4/mqdefault.jpg"
        },
        {
            "video_id": "O5nHR3ryPOo",
            "title": "Slugterra Episode 37(Part 5) in hindi #Slugterra #Hindi",
            "likes": "3470",
            "views": "503062",
            "thumbnail": "https://i.ytimg.com/vi/O5nHR3ryPOo/mqdefault.jpg"
        },
        {
            "video_id": "XBpvxpS2ppg",
            "title": "Slugterra Episode 37(Part 6) in hindi #Slugterra #Hindi",
            "likes": "3930",
            "views": "452396",
            "thumbnail": "https://i.ytimg.com/vi/XBpvxpS2ppg/mqdefault.jpg"
        },
        {
            "video_id": "WnpoMx20RCI",
            "title": "Slugterra Episode 38(Part 1) in hindi #Slugterra #Hindi",
            "likes": "4177",
            "views": "443878",
            "thumbnail": "https://i.ytimg.com/vi/WnpoMx20RCI/mqdefault.jpg"
        },
        {
            "video_id": "hhSzTVoB5_s",
            "title": "Slugterra Episode 38(Part 2) in hindi #Slugterra #Hindi",
            "likes": "2968",
            "views": "410775",
            "thumbnail": "https://i.ytimg.com/vi/hhSzTVoB5_s/mqdefault.jpg"
        },
        {
            "video_id": "857Kjj-usVc",
            "title": "Slugterra Episode 38(Part 3) in hindi #Slugterra #Hindi",
            "likes": "3730",
            "views": "401622",
            "thumbnail": "https://i.ytimg.com/vi/857Kjj-usVc/mqdefault.jpg"
        },
        {
            "video_id": "pZKZxmDu6Qk",
            "title": "Slugterra Episode 38(Part 4) in hindi #Slugterra #Hindi",
            "likes": "3301",
            "views": "390589",
            "thumbnail": "https://i.ytimg.com/vi/pZKZxmDu6Qk/mqdefault.jpg"
        },
        {
            "video_id": "qPxj-mJ_ssM",
            "title": "Slugterra Episode 38(Part 5) in hindi #Slugterra #Hindi",
            "likes": "2944",
            "views": "401495",
            "thumbnail": "https://i.ytimg.com/vi/qPxj-mJ_ssM/mqdefault.jpg"
        },
        {
            "video_id": "lo_XS1L2UF8",
            "title": "Slugterra Episode 38(Part 6) in hindi #Slugterra #Hindi",
            "likes": "3532",
            "views": "420557",
            "thumbnail": "https://i.ytimg.com/vi/lo_XS1L2UF8/mqdefault.jpg"
        },
        {
            "video_id": "bq6S3wTEmSY",
            "title": "Slugterra Episode 39(Part 1) in hindi #Slugterra #Hindi",
            "likes": "3889",
            "views": "447481",
            "thumbnail": "https://i.ytimg.com/vi/bq6S3wTEmSY/mqdefault.jpg"
        },
        {
            "video_id": "LZfKV4nG1mg",
            "title": "Slugterra Episode 39(Part 2) in hindi #Slugterra #Hindi",
            "likes": "4696",
            "views": "562303",
            "thumbnail": "https://i.ytimg.com/vi/LZfKV4nG1mg/mqdefault.jpg"
        },
        {
            "video_id": "vS471SfsDOs",
            "title": "Slugterra Episode 39(Part 3) in hindi #Slugterra #Hindi",
            "likes": "4009",
            "views": "469181",
            "thumbnail": "https://i.ytimg.com/vi/vS471SfsDOs/mqdefault.jpg"
        },
        {
            "video_id": "5bqxG0dhnL8",
            "title": "Slugterra Episode 39(Part 4) in hindi #Slugterra #Hindi",
            "likes": "3710",
            "views": "432520",
            "thumbnail": "https://i.ytimg.com/vi/5bqxG0dhnL8/mqdefault.jpg"
        },
        {
            "video_id": "Dz-KvxNkv9g",
            "title": "Slugterra Episode 39(Part 5) in hindi #Slugterra #Hindi",
            "likes": "3174",
            "views": "447737",
            "thumbnail": "https://i.ytimg.com/vi/Dz-KvxNkv9g/mqdefault.jpg"
        },
        {
            "video_id": "D10B-SSiXv4",
            "title": "Slugterra Episode 39(Part 6) in hindi #Slugterra #Hindi",
            "likes": "5070",
            "views": "441366",
            "thumbnail": "https://i.ytimg.com/vi/D10B-SSiXv4/mqdefault.jpg"
        },
        {
            "video_id": "HN5KT7NQTSE",
            "title": "Slugterra Episode 40 Ghoul From Beyond in hindi #Slugterra #Hindi",
            "likes": "13645",
            "views": "1063959",
            "thumbnail": "https://i.ytimg.com/vi/HN5KT7NQTSE/mqdefault.jpg"
        },
        {
            "video_id": "0LLgxtPmB88",
            "title": "Slugterra Episode 41 Return Of The Elementals in hindi #Slugterra #Hindi",
            "likes": "9742",
            "views": "964920",
            "thumbnail": "https://i.ytimg.com/vi/0LLgxtPmB88/mqdefault.jpg"
        },
        {
            "video_id": "c1lcpYCu0Zc",
            "title": "Slugterra Episode 42 Slug Fu Showdown in hindi #Slugterra #Hindi",
            "likes": "10653",
            "views": "792898",
            "thumbnail": "https://i.ytimg.com/vi/c1lcpYCu0Zc/mqdefault.jpg"
        },
        {
            "video_id": "VV8A6qOsggs",
            "title": "Slugterra Episode 43 in hindi #Slugterra #Hindi",
            "likes": "15016",
            "views": "1139128",
            "thumbnail": "https://i.ytimg.com/vi/VV8A6qOsggs/mqdefault.jpg"
        },
        {
            "video_id": "-SkD2m-RV_g",
            "title": "Slugterra Episode 44(Part 1) #Slugterra",
            "likes": "3863",
            "views": "456436",
            "thumbnail": "https://i.ytimg.com/vi/-SkD2m-RV_g/mqdefault.jpg"
        },
        {
            "video_id": "rU4CTCjR7uk",
            "title": "Slugterra Episode 44(Part 2) #Slugterra",
            "likes": "2270",
            "views": "311830",
            "thumbnail": "https://i.ytimg.com/vi/rU4CTCjR7uk/mqdefault.jpg"
        },
        {
            "video_id": "rIuz5WbmxeI",
            "title": "Slugterra Episode 44(Part 3) #Slugterra",
            "likes": "1705",
            "views": "271132",
            "thumbnail": "https://i.ytimg.com/vi/rIuz5WbmxeI/mqdefault.jpg"
        },
        {
            "video_id": "5t-KXi3JbDg",
            "title": "Slugterra Episode 44(Part 4) #Slugterra",
            "likes": "1635",
            "views": "259784",
            "thumbnail": "https://i.ytimg.com/vi/5t-KXi3JbDg/mqdefault.jpg"
        },
        {
            "video_id": "MCg1fARdRLI",
            "title": "Slugterra Episode 44(Part 5) #Slugterra",
            "likes": "1700",
            "views": "244481",
            "thumbnail": "https://i.ytimg.com/vi/MCg1fARdRLI/mqdefault.jpg"
        },
        {
            "video_id": "LozbgVYioLs",
            "title": "Slugterra Episode 44(Part 6) #Slugterra",
            "likes": "1777",
            "views": "252085",
            "thumbnail": "https://i.ytimg.com/vi/LozbgVYioLs/mqdefault.jpg"
        },
        {
            "video_id": "91nHkTdk4Mk",
            "title": "Slugterra Episode 45 #Slugterra",
            "likes": "5292",
            "views": "518134",
            "thumbnail": "https://i.ytimg.com/vi/91nHkTdk4Mk/mqdefault.jpg"
        },
        {
            "video_id": "rMzhGbNEguI",
            "title": "Slugterra Episode 46 #Slugterra",
            "likes": "4988",
            "views": "419061",
            "thumbnail": "https://i.ytimg.com/vi/rMzhGbNEguI/mqdefault.jpg"
        },
        {
            "video_id": "SEzLUVzlnZo",
            "title": "Slugterra Episode 47 #Slugterra",
            "likes": "4786",
            "views": "386405",
            "thumbnail": "https://i.ytimg.com/vi/SEzLUVzlnZo/mqdefault.jpg"
        },
        {
            "video_id": "xih3FghdTEo",
            "title": "Slugterra Episode 48 #Slugterra",
            "likes": "3854",
            "views": "331921",
            "thumbnail": "https://i.ytimg.com/vi/xih3FghdTEo/mqdefault.jpg"
        },
        {
            "video_id": "vnjF7Uvw2Gw",
            "title": "Slugterra Episode 49 #Slugterra",
            "likes": "3821",
            "views": "307456",
            "thumbnail": "https://i.ytimg.com/vi/vnjF7Uvw2Gw/mqdefault.jpg"
        },
        {
            "video_id": "M3ZuBpwbk1k",
            "title": "Slugterra Episode 50 #Slugterra",
            "likes": "3681",
            "views": "305249",
            "thumbnail": "https://i.ytimg.com/vi/M3ZuBpwbk1k/mqdefault.jpg"
        },
        {
            "video_id": "FLyTg0ecjDs",
            "title": "Slugterra Episode 51 #Slugterra",
            "likes": "3472",
            "views": "268569",
            "thumbnail": "https://i.ytimg.com/vi/FLyTg0ecjDs/mqdefault.jpg"
        },
        {
            "video_id": "1uV4_0sApfA",
            "title": "Slugterra Episode 52 #Slugterra",
            "likes": "3289",
            "views": "272840",
            "thumbnail": "https://i.ytimg.com/vi/1uV4_0sApfA/mqdefault.jpg"
        },
        {
            "video_id": "m7g53p0ojbY",
            "title": "Slugterra Episode 53  #Slugterra",
            "likes": "2840",
            "views": "233597",
            "thumbnail": "https://i.ytimg.com/vi/m7g53p0ojbY/mqdefault.jpg"
        },
        {
            "video_id": "N-SADlfQI9Q",
            "title": "Slugterra Episode 54 #Slugterra",
            "likes": "3286",
            "views": "283946",
            "thumbnail": "https://i.ytimg.com/vi/N-SADlfQI9Q/mqdefault.jpg"
        },
        {
            "video_id": "nGhCme96v04",
            "title": "Slugterra Episode 55 #Slugterra",
            "likes": "3424",
            "views": "285215",
            "thumbnail": "https://i.ytimg.com/vi/nGhCme96v04/mqdefault.jpg"
        },
        {
            "video_id": "BOpbqEwV7iU",
            "title": "Slugterra Episode 56(Part 1) in hindi #Slugterra #Hindi",
            "likes": "1858",
            "views": "214263",
            "thumbnail": "https://i.ytimg.com/vi/BOpbqEwV7iU/mqdefault.jpg"
        },
        {
            "video_id": "mZC6tDj20t4",
            "title": "Slugterra Episode 56(Part 2) in hindi #Slugterra #Hindi",
            "likes": "1705",
            "views": "182931",
            "thumbnail": "https://i.ytimg.com/vi/mZC6tDj20t4/mqdefault.jpg"
        },
        {
            "video_id": "BY6W5GNiW8U",
            "title": "Slugterra Episode 56(Part 3) in hindi #Slugterra #Hindi",
            "likes": "1419",
            "views": "165447",
            "thumbnail": "https://i.ytimg.com/vi/BY6W5GNiW8U/mqdefault.jpg"
        },
        {
            "video_id": "ryd4Mkj9cm4",
            "title": "Slugterra Episode 56(Part 4) in hindi #Slugterra #Hindi",
            "likes": "1479",
            "views": "160313",
            "thumbnail": "https://i.ytimg.com/vi/ryd4Mkj9cm4/mqdefault.jpg"
        },
        {
            "video_id": "NkOtozwPhfw",
            "title": "Slugterra Episode 56(Part 5) in hindi #Slugterra #Hindi",
            "likes": "1123",
            "views": "152823",
            "thumbnail": "https://i.ytimg.com/vi/NkOtozwPhfw/mqdefault.jpg"
        },
        {
            "video_id": "MJM4RiwUPJY",
            "title": "Slugterra Episode 57(Part 1) in hindi #Slugterra #Hindi",
            "likes": "626",
            "views": "123718",
            "thumbnail": "https://i.ytimg.com/vi/MJM4RiwUPJY/mqdefault.jpg"
        },
        {
            "video_id": "O3ivliDEzbY",
            "title": "Slugterra Episode 57(Part 2) in hindi #Slugterra #Hindi",
            "likes": "1130",
            "views": "141252",
            "thumbnail": "https://i.ytimg.com/vi/O3ivliDEzbY/mqdefault.jpg"
        },
        {
            "video_id": "DBYzAwwPexo",
            "title": "Slugterra Episode 57(Part 3 ) in hindi #Slugterra #Hindi",
            "likes": "1298",
            "views": "138099",
            "thumbnail": "https://i.ytimg.com/vi/DBYzAwwPexo/mqdefault.jpg"
        },
        {
            "video_id": "iae9gzsQy4Y",
            "title": "Slugterra Episode 57(Part 4) in hindi #Slugterra #Hindi",
            "likes": "1197",
            "views": "137740",
            "thumbnail": "https://i.ytimg.com/vi/iae9gzsQy4Y/mqdefault.jpg"
        },
        {
            "video_id": "Jq6BDHMW9eM",
            "title": "Slugterra Episode 57(Part 5) in hindi #Slugterra #Hindi",
            "likes": "1317",
            "views": "137212",
            "thumbnail": "https://i.ytimg.com/vi/Jq6BDHMW9eM/mqdefault.jpg"
        },
        {
            "video_id": "6tD03wR_JSA",
            "title": "Slugterra Episode 58(Part 1) in hindi #Slugterra #Hindi",
            "likes": "1333",
            "views": "147745",
            "thumbnail": "https://i.ytimg.com/vi/6tD03wR_JSA/mqdefault.jpg"
        },
        {
            "video_id": "xEFth93zxPI",
            "title": "Slugterra Episode 58(Part 2) in hindi #Slugterra #Hindi",
            "likes": "969",
            "views": "131838",
            "thumbnail": "https://i.ytimg.com/vi/xEFth93zxPI/mqdefault.jpg"
        },
        {
            "video_id": "odLaorPMJgQ",
            "title": "Slugterra Episode 58(Part 3) in hindi #Slugterra #Hindi",
            "likes": "1379",
            "views": "131098",
            "thumbnail": "https://i.ytimg.com/vi/odLaorPMJgQ/mqdefault.jpg"
        },
        {
            "video_id": "INNeUtyfhR4",
            "title": "Slugterra Episode 58(Part 4) in hindi #Slugterra #Hindi",
            "likes": "1138",
            "views": "133178",
            "thumbnail": "https://i.ytimg.com/vi/INNeUtyfhR4/mqdefault.jpg"
        },
        {
            "video_id": "r7yhpbJ-cs4",
            "title": "Slugterra Episode 58(Part 5) in hindi #Slugterra #Hindi",
            "likes": "1029",
            "views": "131207",
            "thumbnail": "https://i.ytimg.com/vi/r7yhpbJ-cs4/mqdefault.jpg"
        },
        {
            "video_id": "lHBuUJ641YY",
            "title": "Slugterra Episode 59(Part 1) in hindi #Slugterra #Hindi",
            "likes": "1098",
            "views": "137902",
            "thumbnail": "https://i.ytimg.com/vi/lHBuUJ641YY/mqdefault.jpg"
        },
        {
            "video_id": "gMBdtFGhMkA",
            "title": "Slugterra Episode 59(Part 2) in hindi #Slugterra #Hindi,",
            "likes": "1157",
            "views": "134465",
            "thumbnail": "https://i.ytimg.com/vi/gMBdtFGhMkA/mqdefault.jpg"
        },
        {
            "video_id": "49qJABb40_g",
            "title": "Slugterra Episode 59(Part 3) in hindi #Slugterra #Hindi",
            "likes": "946",
            "views": "134586",
            "thumbnail": "https://i.ytimg.com/vi/49qJABb40_g/mqdefault.jpg"
        },
        {
            "video_id": "iVnrdGpHRk4",
            "title": "Slugterra Episode 59(Part 4) in hindi #Slugterra #Hindi",
            "likes": "999",
            "views": "135269",
            "thumbnail": "https://i.ytimg.com/vi/iVnrdGpHRk4/mqdefault.jpg"
        },
        {
            "video_id": "lN7pJojhU1w",
            "title": "Slugterra Episode 59(Part 5) in hindi #Slugterra #Hindi",
            "likes": "1031",
            "views": "136098",
            "thumbnail": "https://i.ytimg.com/vi/lN7pJojhU1w/mqdefault.jpg"
        },
        {
            "video_id": "VdW3edyQYTc",
            "title": "Slugterra Episode 60(Part 1) in hindi #Slugterra #Hindi",
            "likes": "1374",
            "views": "168043",
            "thumbnail": "https://i.ytimg.com/vi/VdW3edyQYTc/mqdefault.jpg"
        },
        {
            "video_id": "3bqWhl5NVuw",
            "title": "Slugterra Episode 60(Part 2) in hindi #Slugterra #Hindi",
            "likes": "1285",
            "views": "151102",
            "thumbnail": "https://i.ytimg.com/vi/3bqWhl5NVuw/mqdefault.jpg"
        },
        {
            "video_id": "PhxE2zjvmAE",
            "title": "Slugterra Episode 60(Part 3) in hindi #Slugterra #Hindi",
            "likes": "1424",
            "views": "152889",
            "thumbnail": "https://i.ytimg.com/vi/PhxE2zjvmAE/mqdefault.jpg"
        },
        {
            "video_id": "tTpC-CrSuJI",
            "title": "Slugterra Episode 60(Part 4) in hindi #Slugterra #Hindi",
            "likes": "1657",
            "views": "174687",
            "thumbnail": "https://i.ytimg.com/vi/tTpC-CrSuJI/mqdefault.jpg"
        },
        {
            "video_id": "E0tXwTQKH_s",
            "title": "Slugterra Episode 60(Part 5) in hindi #Slugterra #Hindi",
            "likes": "2769",
            "views": "234690",
            "thumbnail": "https://i.ytimg.com/vi/E0tXwTQKH_s/mqdefault.jpg"
        },
        {
            "video_id": "NlgVV5D-GDI",
            "title": "Why Slugterra Stopped? #slugterra #hindi #ssrecaps",
            "likes": "3955",
            "views": "189621",
            "thumbnail": "https://i.ytimg.com/vi/NlgVV5D-GDI/mqdefault.jpg"
        },
        {
            "video_id": "PWWaWaVaPTg",
            "title": "Slugterra Ascension Episode 1 trapped #slugterra #sr_recaps #slugterranew",
            "likes": "283",
            "views": "43711",
            "thumbnail": "https://i.ytimg.com/vi/PWWaWaVaPTg/mqdefault.jpg"
        },
        {
            "video_id": "Mb40_oov0pM",
            "title": "Slugterra Ascension Episode 2 Iced Out #slugterra #sr_recaps #slugterranew",
            "likes": "168",
            "views": "25044",
            "thumbnail": "https://i.ytimg.com/vi/Mb40_oov0pM/mqdefault.jpg"
        },
        {
            "video_id": "WF9745QrK7M",
            "title": "Slugterra Ascension Episode 3 Crossroads #slugterra #sr_recaps #slugterranew",
            "likes": "124",
            "views": "21069",
            "thumbnail": "https://i.ytimg.com/vi/WF9745QrK7M/mqdefault.jpg"
        },
        {
            "video_id": "F3DRLhR-jAQ",
            "title": "Slugterra Ascension Episode 4 Tunneled #slugterra #sr_recaps #slugterranew",
            "likes": "115",
            "views": "18561",
            "thumbnail": "https://i.ytimg.com/vi/F3DRLhR-jAQ/mqdefault.jpg"
        },
        {
            "video_id": "nOg9rF92I_s",
            "title": "Slugterra Ascension Episode 5 Follow that Flopper #slugterra #sr_recaps #slugterranew",
            "likes": "112",
            "views": "22107",
            "thumbnail": "https://i.ytimg.com/vi/nOg9rF92I_s/mqdefault.jpg"
        },
        {
            "video_id": "DoJOCrbT_iQ",
            "title": "Slugterra Ascension Episode 6 Hidden Depths #slugterra #sr_recaps #slugterranew",
            "likes": "110",
            "views": "16891",
            "thumbnail": "https://i.ytimg.com/vi/DoJOCrbT_iQ/mqdefault.jpg"
        },
        {
            "video_id": "_oSSxbz3mtM",
            "title": "Slugterra Ascension Episode 7 Slug Stalker #slugterra #sr_recaps #slugterranew",
            "likes": "127",
            "views": "21772",
            "thumbnail": "https://i.ytimg.com/vi/_oSSxbz3mtM/mqdefault.jpg"
        },
        {
            "video_id": "SCOorp7X7WA",
            "title": "Slugterra Ascension Episode 8 Exit Strategy #slugterra #sr_recaps #slugterranew",
            "likes": "86",
            "views": "15373",
            "thumbnail": "https://i.ytimg.com/vi/SCOorp7X7WA/mqdefault.jpg"
        },
        {
            "video_id": "9wcTiOoh4Gc",
            "title": "Slugterra Ascension Episode 9 Slippery Slope #slugterra #sr_recaps #slugterranew",
            "likes": "111",
            "views": "14937",
            "thumbnail": "https://i.ytimg.com/vi/9wcTiOoh4Gc/mqdefault.jpg"
        },
        {
            "video_id": "TCSANCyPRNc",
            "title": "Slugterra Ascension Episode 10 Fire Inside #slugterra #sr_recaps #slugterranew",
            "likes": "96",
            "views": "15304",
            "thumbnail": "https://i.ytimg.com/vi/TCSANCyPRNc/mqdefault.jpg"
        },
        {
            "video_id": "pprfzl4D-sw",
            "title": "Slugterra Ascension Episode 11 Fry Voltage #slugterra #sr_recaps #slugterranew",
            "likes": "100",
            "views": "14876",
            "thumbnail": "https://i.ytimg.com/vi/pprfzl4D-sw/mqdefault.jpg"
        },
        {
            "video_id": "w7wY8XwEOy4",
            "title": "Slugterra Ascension Episode 12 Spinning Wheels #slugterra #sr_recaps #slugterranew",
            "likes": "98",
            "views": "14087",
            "thumbnail": "https://i.ytimg.com/vi/w7wY8XwEOy4/mqdefault.jpg"
        },
        {
            "video_id": "JCO2fgWxWNA",
            "title": "Slugterra Ascension Episode 13 Slugball #slugterra #sr_recaps #slugterranew",
            "likes": "92",
            "views": "13683",
            "thumbnail": "https://i.ytimg.com/vi/JCO2fgWxWNA/mqdefault.jpg"
        },
        {
            "video_id": "-tMgxAK-eSE",
            "title": "Slugterra Ascension Episode 14 Stink Wave #slugterra #sr_recaps #slugterranew",
            "likes": "73",
            "views": "13639",
            "thumbnail": "https://i.ytimg.com/vi/-tMgxAK-eSE/mqdefault.jpg"
        },
        {
            "video_id": "7pA4qj5U0aw",
            "title": "Slugterra Ascension Episode 15 Bridge Too Far #slugterra #sr_recaps #slugterranew",
            "likes": "87",
            "views": "14074",
            "thumbnail": "https://i.ytimg.com/vi/7pA4qj5U0aw/mqdefault.jpg"
        },
        {
            "video_id": "12rnxBQ79bE",
            "title": "Slugterra Ascension Episode 16 From the Deep  #slugterra #sr_recaps #slugterranew",
            "likes": "89",
            "views": "13672",
            "thumbnail": "https://i.ytimg.com/vi/12rnxBQ79bE/mqdefault.jpg"
        },
        {
            "video_id": "FGV9X14YtXw",
            "title": "Slugterra Ascension Episode 17 Cover of Night #slugterra #sr_recaps #slugterranew",
            "likes": "92",
            "views": "15148",
            "thumbnail": "https://i.ytimg.com/vi/FGV9X14YtXw/mqdefault.jpg"
        },
        {
            "video_id": "nmFzaaNAn74",
            "title": "Slugterra Ascension Episode 18 Save that Slug #slugterra #sr_recaps #slugterranew",
            "likes": "80",
            "views": "15293",
            "thumbnail": "https://i.ytimg.com/vi/nmFzaaNAn74/mqdefault.jpg"
        },
        {
            "video_id": "R4xNXUVq97k",
            "title": "Slugterra Ascension Episode 19 Frost Warning #slugterra #sr_recaps #slugterranew",
            "likes": "108",
            "views": "23041",
            "thumbnail": "https://i.ytimg.com/vi/R4xNXUVq97k/mqdefault.jpg"
        },
        {
            "video_id": "X3s7YyviP6A",
            "title": "Slugterra Ascension Episode 20 Battle Cry #slugterra #sr_recaps #slugterranew",
            "likes": "307",
            "views": "60557",
            "thumbnail": "https://i.ytimg.com/vi/X3s7YyviP6A/mqdefault.jpg"
        }
    ]
}