{
    "playlist_id": "PL5FlnLCqzKemKFzoJmhDfyQFgB3J10QUQ",
    "playlist_title": "TRANSFORMERS PRIME all episodes in Hindi",
    "playlist_published_at": "2020-05-20T13:25:34Z",
    "playlist_item_count": 207,
    "channel_name": "Transformers Prime Video",
    "videos": [
        {
            "video_id": "9CS2JIKVIZU",
            "title": "Transformers Prime Episode 1 (1 of 3 Part) _Darkness Rising, Part 1_ in Hindi",
            "likes": "15594",
            "views": "1579186",
            "thumbnail": "https://i.ytimg.com/vi/9CS2JIKVIZU/mqdefault.jpg"
        },
        {
            "video_id": "sHVkXovXCc0",
            "title": "Transformers Prime Episode 1 (2 of 3 Part) _Darkness Rising, Part 1_ in Hindi",
            "likes": "6708",
            "views": "766326",
            "thumbnail": "https://i.ytimg.com/vi/sHVkXovXCc0/mqdefault.jpg"
        },
        {
            "video_id": "0a13MhMd9aI",
            "title": "Transformers Prime Episode 1 (3 of 3 Part) _Darkness Rising, Part 1_ in Hindi",
            "likes": "7236",
            "views": "745400",
            "thumbnail": "https://i.ytimg.com/vi/0a13MhMd9aI/mqdefault.jpg"
        },
        {
            "video_id": "4TCi_PU02zc",
            "title": "Transformers Prime Episode 2 (1 of 3 Part) _Darkness Rising, Part 2_ in Hindi",
            "likes": "6670",
            "views": "680589",
            "thumbnail": "https://i.ytimg.com/vi/4TCi_PU02zc/mqdefault.jpg"
        },
        {
            "video_id": "hGBVvTyEWSo",
            "title": "Transformers Prime Episode 2 (2 of 3 Part) _Darkness Rising, Part 2_ in Hindi",
            "likes": "4803",
            "views": "599208",
            "thumbnail": "https://i.ytimg.com/vi/hGBVvTyEWSo/mqdefault.jpg"
        },
        {
            "video_id": "vf5fzVZ3e7Q",
            "title": "Transformers Prime Episode 2 (3 of 3 Part) _Darkness Rising, Part 2_ in Hindi",
            "likes": "4762",
            "views": "539859",
            "thumbnail": "https://i.ytimg.com/vi/vf5fzVZ3e7Q/mqdefault.jpg"
        },
        {
            "video_id": "IWHpsLD6Vo8",
            "title": "Transformers Prime Episode 3 (1 of 3 Part) _Darkness Rising, Part 3_ in Hindi",
            "likes": "5073",
            "views": "534727",
            "thumbnail": "https://i.ytimg.com/vi/IWHpsLD6Vo8/mqdefault.jpg"
        },
        {
            "video_id": "ypGDNKnH2RM",
            "title": "Transformers Prime Episode 3 (2 of 3 Part) _Darkness Rising, Part 3_ in Hindi",
            "likes": "4547",
            "views": "488381",
            "thumbnail": "https://i.ytimg.com/vi/ypGDNKnH2RM/mqdefault.jpg"
        },
        {
            "video_id": "ca4OOtOnUMU",
            "title": "Transformers Prime Episode 3 (3 of 3 Part) _Darkness Rising, Part 3_ in Hindi",
            "likes": "4423",
            "views": "501034",
            "thumbnail": "https://i.ytimg.com/vi/ca4OOtOnUMU/mqdefault.jpg"
        },
        {
            "video_id": "1vC1SYMRT_Q",
            "title": "Transformers Prime Episode 4 (1 of 3 Part)  _Darkness Rising, Part 4_ in Hindi",
            "likes": "3981",
            "views": "450918",
            "thumbnail": "https://i.ytimg.com/vi/1vC1SYMRT_Q/mqdefault.jpg"
        },
        {
            "video_id": "A1aZl8xY060",
            "title": "Transformers Prime Episode 4 (2 of  3 Part) _Darkness Rising, Part 4_ in Hindi",
            "likes": "3706",
            "views": "434635",
            "thumbnail": "https://i.ytimg.com/vi/A1aZl8xY060/mqdefault.jpg"
        },
        {
            "video_id": "tuD9VIYwA4k",
            "title": "Transformers Prime Episode 4 (3 of  3 Part)  _Darkness Rising, Part 4_ in Hindi",
            "likes": "4879",
            "views": "462051",
            "thumbnail": "https://i.ytimg.com/vi/tuD9VIYwA4k/mqdefault.jpg"
        },
        {
            "video_id": "g7U7yGhQy3w",
            "title": "Transformers Prime Episode 5 (1 of 3 Part)  _Darkness Rising, Part 5_ in Hindi",
            "likes": "4467",
            "views": "426286",
            "thumbnail": "https://i.ytimg.com/vi/g7U7yGhQy3w/mqdefault.jpg"
        },
        {
            "video_id": "gVzbuRgZNNI",
            "title": "Transformers Prime Episode 5 (2 of 3 Part) _Darkness Rising, Part 5_ in Hindi",
            "likes": "3508",
            "views": "400585",
            "thumbnail": "https://i.ytimg.com/vi/gVzbuRgZNNI/mqdefault.jpg"
        },
        {
            "video_id": "VG1uT9ocg-g",
            "title": "Transformers Prime Episode 5 (3 of 3 Part) _Darkness Rising, Part 5_ in Hindi",
            "likes": "4467",
            "views": "426961",
            "thumbnail": "https://i.ytimg.com/vi/VG1uT9ocg-g/mqdefault.jpg"
        },
        {
            "video_id": "Qnfm4LjSvgQ",
            "title": "Transformers Prime Episode 6 (1 of 3 Part) _Masters and Students_ in Hindi",
            "likes": "4593",
            "views": "401856",
            "thumbnail": "https://i.ytimg.com/vi/Qnfm4LjSvgQ/mqdefault.jpg"
        },
        {
            "video_id": "2hgateTmOAs",
            "title": "Transformers Prime Episode 6 (2 of 3 Part) _Masters and Students_ in Hindi",
            "likes": "4618",
            "views": "443787",
            "thumbnail": "https://i.ytimg.com/vi/2hgateTmOAs/mqdefault.jpg"
        },
        {
            "video_id": "Ut3STFUgRGU",
            "title": "Transformers Prime Episode 6 (3 of 3 Part) _Masters and Students_ in Hindi",
            "likes": "4039",
            "views": "460111",
            "thumbnail": "https://i.ytimg.com/vi/Ut3STFUgRGU/mqdefault.jpg"
        },
        {
            "video_id": "GIhlf7mwfKM",
            "title": "Transformers Prime Episode 7 (1 of 3 Part) _Scrapheap_ in Hindi",
            "likes": "3631",
            "views": "421262",
            "thumbnail": "https://i.ytimg.com/vi/GIhlf7mwfKM/mqdefault.jpg"
        },
        {
            "video_id": "O2b9Ava9VUk",
            "title": "Transformers Prime Episode 7 (2 of 3 Part) _Scrapheap_ in Hindi",
            "likes": "3247",
            "views": "387125",
            "thumbnail": "https://i.ytimg.com/vi/O2b9Ava9VUk/mqdefault.jpg"
        },
        {
            "video_id": "WiOIZPtqQBA",
            "title": "Transformers Prime Episode 7 (3 of 3 Part) _Scrapheap_ in Hindi",
            "likes": "3049",
            "views": "361800",
            "thumbnail": "https://i.ytimg.com/vi/WiOIZPtqQBA/mqdefault.jpg"
        },
        {
            "video_id": "A5wsjrvB7_w",
            "title": "Transformers Prime Episode 8 (1 of 3 Part) _Con Job_ in Hindi",
            "likes": "4135",
            "views": "388154",
            "thumbnail": "https://i.ytimg.com/vi/A5wsjrvB7_w/mqdefault.jpg"
        },
        {
            "video_id": "i3YN0k1hKqk",
            "title": "Transformers Prime Episode 8 (2 of 3 Part) _Con Job_ in Hindi",
            "likes": "4024",
            "views": "359383",
            "thumbnail": "https://i.ytimg.com/vi/i3YN0k1hKqk/mqdefault.jpg"
        },
        {
            "video_id": "hxLoeJw0tQo",
            "title": "Transformers Prime Episode 8 (3 of 3 Part) _Con Job_ in Hindi",
            "likes": "3525",
            "views": "344395",
            "thumbnail": "https://i.ytimg.com/vi/hxLoeJw0tQo/mqdefault.jpg"
        },
        {
            "video_id": "Xn_7lDCzuPc",
            "title": "Transformers Prime Episode 9 (1 of 3 Part) _Convoy_ in Hindi",
            "likes": "3637",
            "views": "353871",
            "thumbnail": "https://i.ytimg.com/vi/Xn_7lDCzuPc/mqdefault.jpg"
        },
        {
            "video_id": "j6HZIUfBe9A",
            "title": "Transformers Prime Episode 9 (2 of 3 Part) _Convoy_ in Hindi",
            "likes": "3152",
            "views": "333313",
            "thumbnail": "https://i.ytimg.com/vi/j6HZIUfBe9A/mqdefault.jpg"
        },
        {
            "video_id": "oFgx1_omaI0",
            "title": "Transformers Prime Episode 9 (3 of 3 Part) _Convoy_ in Hindi",
            "likes": "3320",
            "views": "327953",
            "thumbnail": "https://i.ytimg.com/vi/oFgx1_omaI0/mqdefault.jpg"
        },
        {
            "video_id": "OBwnMQu6Zxk",
            "title": "Transformers Prime Episode 10 (1 of 3 Part) _Deus Ex Machina_ in Hindi",
            "likes": "3671",
            "views": "325469",
            "thumbnail": "https://i.ytimg.com/vi/OBwnMQu6Zxk/mqdefault.jpg"
        },
        {
            "video_id": "hKPweiht81U",
            "title": "Transformers Prime Episode 10 (2 of 3 Part) _Deus Ex Machina_ in Hindi",
            "likes": "3080",
            "views": "306590",
            "thumbnail": "https://i.ytimg.com/vi/hKPweiht81U/mqdefault.jpg"
        },
        {
            "video_id": "jm23_OMHG2c",
            "title": "Transformers Prime Episode 10 (3 of 3 Part) _Deus Ex Machina_ in Hindi",
            "likes": "3019",
            "views": "316287",
            "thumbnail": "https://i.ytimg.com/vi/jm23_OMHG2c/mqdefault.jpg"
        },
        {
            "video_id": "Ri0PhVEgMKU",
            "title": "Transformers Prime Episode 11 (1 of 3 Part) _Speed Metal_ in Hindi",
            "likes": "3309",
            "views": "317968",
            "thumbnail": "https://i.ytimg.com/vi/Ri0PhVEgMKU/mqdefault.jpg"
        },
        {
            "video_id": "mGL99Ytlwj8",
            "title": "Transformers Prime Episode 11 (2 of 3 Part) _Speed Metal_ in Hindi",
            "likes": "3188",
            "views": "299963",
            "thumbnail": "https://i.ytimg.com/vi/mGL99Ytlwj8/mqdefault.jpg"
        },
        {
            "video_id": "19xGBsKTbLY",
            "title": "Transformers Prime Episode 11 (3 of 3 Part) _Speed Metal_ in Hindi",
            "likes": "3003",
            "views": "299984",
            "thumbnail": "https://i.ytimg.com/vi/19xGBsKTbLY/mqdefault.jpg"
        },
        {
            "video_id": "Tx5BfFqY0IE",
            "title": "Transformers Prime Episode 12 (1 of 3 Part) _Predatory_ in Hindi",
            "likes": "2877",
            "views": "295498",
            "thumbnail": "https://i.ytimg.com/vi/Tx5BfFqY0IE/mqdefault.jpg"
        },
        {
            "video_id": "_1UQyokv-9c",
            "title": "Transformers Prime Episode 12 (2 of 3 Part) _Predatory_ in Hindi",
            "likes": "2474",
            "views": "268017",
            "thumbnail": "https://i.ytimg.com/vi/_1UQyokv-9c/mqdefault.jpg"
        },
        {
            "video_id": "KxtxoINvwtk",
            "title": "Transformers Prime Episode 12 (3 of 3 Part) _Predatory_ in Hindi",
            "likes": "2316",
            "views": "263470",
            "thumbnail": "https://i.ytimg.com/vi/KxtxoINvwtk/mqdefault.jpg"
        },
        {
            "video_id": "n0-QKLWyfE4",
            "title": "Transformers Prime Episode 13 (1 of 3 Part) _Sick Mind_ in Hindi",
            "likes": "3388",
            "views": "293607",
            "thumbnail": "https://i.ytimg.com/vi/n0-QKLWyfE4/mqdefault.jpg"
        },
        {
            "video_id": "36DLZy_Tg0A",
            "title": "Transformers Prime Episode 13 (2 of 3 Part) _Sick Mind_ in Hindi",
            "likes": "2935",
            "views": "282600",
            "thumbnail": "https://i.ytimg.com/vi/36DLZy_Tg0A/mqdefault.jpg"
        },
        {
            "video_id": "juZ5CntMut8",
            "title": "Transformers Prime Episode 13 (3 of 3 Part) _Sick Mind_ in Hindi",
            "likes": "3184",
            "views": "290582",
            "thumbnail": "https://i.ytimg.com/vi/juZ5CntMut8/mqdefault.jpg"
        },
        {
            "video_id": "0nhGEMoQhH8",
            "title": "Transformers Prime Episode 14 (1 of 3 Part) _Out of His Head_ in Hindi",
            "likes": "3367",
            "views": "288232",
            "thumbnail": "https://i.ytimg.com/vi/0nhGEMoQhH8/mqdefault.jpg"
        },
        {
            "video_id": "5in0RlSOQMw",
            "title": "Transformers Prime Episode 14 (2 of 3 Part) _Out of His Head_ in Hindi",
            "likes": "3265",
            "views": "307899",
            "thumbnail": "https://i.ytimg.com/vi/5in0RlSOQMw/mqdefault.jpg"
        },
        {
            "video_id": "_avFOQIVgZs",
            "title": "Transformers Prime Episode 14 (3 of 3 Part) _Out of His Head_ in Hindi",
            "likes": "3119",
            "views": "311610",
            "thumbnail": "https://i.ytimg.com/vi/_avFOQIVgZs/mqdefault.jpg"
        },
        {
            "video_id": "LKNaXmRgXLw",
            "title": "Transformers Prime Episode 15 (1 of 3 Part) _Shadowzone_  in Hindi",
            "likes": "3320",
            "views": "300503",
            "thumbnail": "https://i.ytimg.com/vi/LKNaXmRgXLw/mqdefault.jpg"
        },
        {
            "video_id": "WdSkkAqf448",
            "title": "Transformers Prime Episode 15 (2 of 3 Part) _Shadowzone_  in Hindi",
            "likes": "2620",
            "views": "269665",
            "thumbnail": "https://i.ytimg.com/vi/WdSkkAqf448/mqdefault.jpg"
        },
        {
            "video_id": "RxZ2N5VZsbU",
            "title": "Transformers Prime Episode 15 (3 of 3 Part) _Shadowzone_  in Hindi",
            "likes": "2896",
            "views": "280655",
            "thumbnail": "https://i.ytimg.com/vi/RxZ2N5VZsbU/mqdefault.jpg"
        },
        {
            "video_id": "lH6fwilV2rg",
            "title": "Transformers Prime Episode 16 (1 of 3 Part) _Operation  Breakdown_ in Hindi",
            "likes": "3378",
            "views": "295368",
            "thumbnail": "https://i.ytimg.com/vi/lH6fwilV2rg/mqdefault.jpg"
        },
        {
            "video_id": "o4aC0yQHzWw",
            "title": "Transformers Prime Episode 16 (2 of 3 Part) _Operation  Breakdown_ in Hindi",
            "likes": "2750",
            "views": "262300",
            "thumbnail": "https://i.ytimg.com/vi/o4aC0yQHzWw/mqdefault.jpg"
        },
        {
            "video_id": "QL2h3Zgkb9k",
            "title": "Transformers Prime Episode 16 (3 of 3 Part) _Operation  Breakdown_ in Hindi",
            "likes": "2778",
            "views": "272169",
            "thumbnail": "https://i.ytimg.com/vi/QL2h3Zgkb9k/mqdefault.jpg"
        },
        {
            "video_id": "uDFVl5B2hbA",
            "title": "Transformers Prime Episode 17 (1 of 3 Part) _Crisscross_ in Hindi",
            "likes": "3034",
            "views": "272200",
            "thumbnail": "https://i.ytimg.com/vi/uDFVl5B2hbA/mqdefault.jpg"
        },
        {
            "video_id": "wccT2Qmcukg",
            "title": "Transformers Prime Episode 17 (2 of 3 Part) _Crisscross_ in Hindi",
            "likes": "2698",
            "views": "242929",
            "thumbnail": "https://i.ytimg.com/vi/wccT2Qmcukg/mqdefault.jpg"
        },
        {
            "video_id": "yOp90w2GHpg",
            "title": "Transformers Prime Episode 17 (3 of 3 Part) _Crisscross_ in Hindi",
            "likes": "2395",
            "views": "245118",
            "thumbnail": "https://i.ytimg.com/vi/yOp90w2GHpg/mqdefault.jpg"
        },
        {
            "video_id": "Yoj_bvCaLo4",
            "title": "Transformers Prime Episode 18 (1 of 3 Part) _Metal Attraction_ in Hindi",
            "likes": "3053",
            "views": "266016",
            "thumbnail": "https://i.ytimg.com/vi/Yoj_bvCaLo4/mqdefault.jpg"
        },
        {
            "video_id": "WnGkLJ47p7I",
            "title": "Transformers Prime Episode 18 (2 of 3 Part) _Metal Attraction_ in Hindi",
            "likes": "2647",
            "views": "268761",
            "thumbnail": "https://i.ytimg.com/vi/WnGkLJ47p7I/mqdefault.jpg"
        },
        {
            "video_id": "Q6jxYj3ryOQ",
            "title": "Transformers Prime Episode 18 (3 of 3 Part) _Metal Attraction_ in Hindi",
            "likes": "2856",
            "views": "263414",
            "thumbnail": "https://i.ytimg.com/vi/Q6jxYj3ryOQ/mqdefault.jpg"
        },
        {
            "video_id": "MXKRnC80QL8",
            "title": "Transformers Prime Episode 19 (1 of 3 Part) _Rock Bottom_ in Hindi",
            "likes": "3110",
            "views": "276877",
            "thumbnail": "https://i.ytimg.com/vi/MXKRnC80QL8/mqdefault.jpg"
        },
        {
            "video_id": "fVB-EXtHayQ",
            "title": "Transformers Prime Episode 19 (2 of 3 Part) _Rock Bottom_ in Hindi",
            "likes": "2355",
            "views": "257210",
            "thumbnail": "https://i.ytimg.com/vi/fVB-EXtHayQ/mqdefault.jpg"
        },
        {
            "video_id": "C5RDLamx3zM",
            "title": "Transformers Prime Episode 19 (3 of 3 Part) _Rock Bottom_ in Hindi",
            "likes": "2363",
            "views": "248111",
            "thumbnail": "https://i.ytimg.com/vi/C5RDLamx3zM/mqdefault.jpg"
        },
        {
            "video_id": "YSX5tvqm-Ws",
            "title": "Transformers Prime Episode 20 (1 of 3 Part) _Partners_ in Hindi",
            "likes": "3307",
            "views": "266159",
            "thumbnail": "https://i.ytimg.com/vi/YSX5tvqm-Ws/mqdefault.jpg"
        },
        {
            "video_id": "nSQAmy1O7wU",
            "title": "Transformers Prime Episode 20 (2 of 3 Part) _Partners_ in Hindi",
            "likes": "2719",
            "views": "246812",
            "thumbnail": "https://i.ytimg.com/vi/nSQAmy1O7wU/mqdefault.jpg"
        },
        {
            "video_id": "a2lUl3LHsV4",
            "title": "Transformers Prime Episode 20 (3 of 3 Part) _Partners_ in Hindi",
            "likes": "2574",
            "views": "245996",
            "thumbnail": "https://i.ytimg.com/vi/a2lUl3LHsV4/mqdefault.jpg"
        },
        {
            "video_id": "axUfAX12NrU",
            "title": "Transformers Prime Episode 21 (1 of 3 Part) _T.M.I._ in Hindi",
            "likes": "2694",
            "views": "255044",
            "thumbnail": "https://i.ytimg.com/vi/axUfAX12NrU/mqdefault.jpg"
        },
        {
            "video_id": "lU6ge12UPfc",
            "title": "Transformers Prime Episode 21 (2 of 3 Part) _T.M.I._ in Hindi",
            "likes": "2780",
            "views": "247022",
            "thumbnail": "https://i.ytimg.com/vi/lU6ge12UPfc/mqdefault.jpg"
        },
        {
            "video_id": "33ipVu9j_Lk",
            "title": "Transformers Prime Episode 21 (3 of 3 Part) _T.M.I._ in Hindi",
            "likes": "2620",
            "views": "252376",
            "thumbnail": "https://i.ytimg.com/vi/33ipVu9j_Lk/mqdefault.jpg"
        },
        {
            "video_id": "LAPBbw7-hDs",
            "title": "Transformers Prime Episode 22 (1 of 3 part)  _Stronger, Faster_ in Hindi",
            "likes": "2923",
            "views": "271851",
            "thumbnail": "https://i.ytimg.com/vi/LAPBbw7-hDs/mqdefault.jpg"
        },
        {
            "video_id": "VNAPdczI2i8",
            "title": "Transformers Prime Episode 22 (2 of 3 part)  _Stronger, Faster_ in Hindi",
            "likes": "3128",
            "views": "283494",
            "thumbnail": "https://i.ytimg.com/vi/VNAPdczI2i8/mqdefault.jpg"
        },
        {
            "video_id": "rg971r5H6Tw",
            "title": "Transformers Prime Episode 22 (3 of 3 part)  _Stronger, Faster_ in Hindi",
            "likes": "3461",
            "views": "283051",
            "thumbnail": "https://i.ytimg.com/vi/rg971r5H6Tw/mqdefault.jpg"
        },
        {
            "video_id": "-9WBpWYhIg0",
            "title": "Transformers Prime Episode 23 (1 of 3 Part) _One Shall Fall_ in Hindi",
            "likes": "3931",
            "views": "314563",
            "thumbnail": "https://i.ytimg.com/vi/-9WBpWYhIg0/mqdefault.jpg"
        },
        {
            "video_id": "y3McMj9NVwM",
            "title": "Transformers Prime Episode 23 (2 of 3 Part) _One Shall Fall_ in Hindi",
            "likes": "3782",
            "views": "342849",
            "thumbnail": "https://i.ytimg.com/vi/y3McMj9NVwM/mqdefault.jpg"
        },
        {
            "video_id": "w29KIhhZ3-M",
            "title": "Transformers Prime Episode 23 (3 of 3 Part) _One Shall Fall_ in Hindi",
            "likes": "3801",
            "views": "367631",
            "thumbnail": "https://i.ytimg.com/vi/w29KIhhZ3-M/mqdefault.jpg"
        },
        {
            "video_id": "GbBSA6nZnzA",
            "title": "Transformers Prime Episode 24 (1 of 3 Part) _One Shall Rise, Part 1_ in Hindi",
            "likes": "3594",
            "views": "311350",
            "thumbnail": "https://i.ytimg.com/vi/GbBSA6nZnzA/mqdefault.jpg"
        },
        {
            "video_id": "QXdXDhM8qSw",
            "title": "Transformers Prime Episode 24 (2 of 3 Part) _One Shall Rise, Part 1_ in Hindi",
            "likes": "3420",
            "views": "317618",
            "thumbnail": "https://i.ytimg.com/vi/QXdXDhM8qSw/mqdefault.jpg"
        },
        {
            "video_id": "TirzlMJgVzI",
            "title": "Transformers Prime Episode 24 (3 of 3 Part) _One Shall Rise, Part 1_ in Hindi",
            "likes": "3798",
            "views": "341821",
            "thumbnail": "https://i.ytimg.com/vi/TirzlMJgVzI/mqdefault.jpg"
        },
        {
            "video_id": "Y4mSZjmoTC8",
            "title": "Transformers Prime Episode 25 (1 of 3 Part) _One Shall Rise, Part 2_ in Hindi",
            "likes": "3094",
            "views": "303901",
            "thumbnail": "https://i.ytimg.com/vi/Y4mSZjmoTC8/mqdefault.jpg"
        },
        {
            "video_id": "v2e1NvEuFtA",
            "title": "Transformers Prime Episode 25 (2 of 3 Part) _One Shall Rise, Part 2_ in Hindi",
            "likes": "3962",
            "views": "318236",
            "thumbnail": "https://i.ytimg.com/vi/v2e1NvEuFtA/mqdefault.jpg"
        },
        {
            "video_id": "8Z8E6DekJn8",
            "title": "Transformers Prime Episode 25 (3 of 3 Part) _One Shall Rise, Part 2_ in Hindi",
            "likes": "3650",
            "views": "317310",
            "thumbnail": "https://i.ytimg.com/vi/8Z8E6DekJn8/mqdefault.jpg"
        },
        {
            "video_id": "3aXseEcsvJM",
            "title": "Transformers Prime Episode 26 (1 of 3 Part) _One Shall Rise, Part 3 (Season 1 Final)_ in Hindi",
            "likes": "3758",
            "views": "321781",
            "thumbnail": "https://i.ytimg.com/vi/3aXseEcsvJM/mqdefault.jpg"
        },
        {
            "video_id": "G9gat1Ko8BY",
            "title": "Transformers Prime Episode 26 (2 of 3 Part) _One Shall Rise, Part 3 (Season 1 Final)_ in Hindi",
            "likes": "3336",
            "views": "334390",
            "thumbnail": "https://i.ytimg.com/vi/G9gat1Ko8BY/mqdefault.jpg"
        },
        {
            "video_id": "qkQhxPEbrgk",
            "title": "Transformers Prime Episode 26 (3 of 3 Part) _One Shall Rise, Part 3 (Season 1 Final)_ in Hindi",
            "likes": "3431",
            "views": "335160",
            "thumbnail": "https://i.ytimg.com/vi/qkQhxPEbrgk/mqdefault.jpg"
        },
        {
            "video_id": "1C0LRie58yI",
            "title": "Transformers Prime Season 2 Episode 1 (1 of 3 Part) _Orion Pax, Part 1_ in Hindi",
            "likes": "5093",
            "views": "400975",
            "thumbnail": "https://i.ytimg.com/vi/1C0LRie58yI/mqdefault.jpg"
        },
        {
            "video_id": "xiOOZvC38IU",
            "title": "Transformers Prime Season 2 Episode 1 (2 of 3 Part) _Orion Pax, Part 1_ in Hindi",
            "likes": "3677",
            "views": "335167",
            "thumbnail": "https://i.ytimg.com/vi/xiOOZvC38IU/mqdefault.jpg"
        },
        {
            "video_id": "F2XZ0FuMwgI",
            "title": "Transformers Prime Season 2 Episode 1 (3 of 3 Part) _Orion Pax, Part 1_ in Hindi",
            "likes": "3068",
            "views": "325687",
            "thumbnail": "https://i.ytimg.com/vi/F2XZ0FuMwgI/mqdefault.jpg"
        },
        {
            "video_id": "at5BPLPf4nM",
            "title": "Transformers Prime Season 2 Episode 2 (1 of 3 Part) _Orion Pax, Part 2_ in Hindi",
            "likes": "3521",
            "views": "313119",
            "thumbnail": "https://i.ytimg.com/vi/at5BPLPf4nM/mqdefault.jpg"
        },
        {
            "video_id": "UhGH9mFGFUM",
            "title": "Transformers Prime Season 2 Episode 2 (2 of 3 Part) _Orion Pax, Part 2_ in Hindi",
            "likes": "3477",
            "views": "301790",
            "thumbnail": "https://i.ytimg.com/vi/UhGH9mFGFUM/mqdefault.jpg"
        },
        {
            "video_id": "x1QYp-zcGck",
            "title": "Transformers Prime Season 2 Episode 2 (3  of 3 Part) _Orion Pax, Part 2_ in Hindi",
            "likes": "3003",
            "views": "304776",
            "thumbnail": "https://i.ytimg.com/vi/x1QYp-zcGck/mqdefault.jpg"
        },
        {
            "video_id": "kKQAlZwXwAo",
            "title": "Transformers Prime Season 2 Episode 3 (1 of 3 Part) _Orion Pax, Part 3_ in Hindi",
            "likes": "2839",
            "views": "298160",
            "thumbnail": "https://i.ytimg.com/vi/kKQAlZwXwAo/mqdefault.jpg"
        },
        {
            "video_id": "EKg11b00F_I",
            "title": "Transformers Prime Season 2 Episode 3 (2 of 3 Part) _Orion Pax, Part 3_ in Hindi",
            "likes": "2673",
            "views": "305627",
            "thumbnail": "https://i.ytimg.com/vi/EKg11b00F_I/mqdefault.jpg"
        },
        {
            "video_id": "2QL4Jk934Uo",
            "title": "Transformers Prime Season 2 Episode 3 (3 of 3 Part) _Orion Pax, Part 3_ in Hindi",
            "likes": "3935",
            "views": "369810",
            "thumbnail": "https://i.ytimg.com/vi/2QL4Jk934Uo/mqdefault.jpg"
        },
        {
            "video_id": "eCzJlR6Umm8",
            "title": "Transformers Prime Season 2 Episode 4 (1 of 3 Part) _Operation_ Bumblebee, Part 1_ in Hindi",
            "likes": "4072",
            "views": "349209",
            "thumbnail": "https://i.ytimg.com/vi/eCzJlR6Umm8/mqdefault.jpg"
        },
        {
            "video_id": "_ZWtSDg6MZs",
            "title": "Transformers Prime Season 2 Episode 4 (2 of 3 Part) _Operation_ Bumblebee, Part 1_ in Hindi",
            "likes": "3109",
            "views": "309082",
            "thumbnail": "https://i.ytimg.com/vi/_ZWtSDg6MZs/mqdefault.jpg"
        },
        {
            "video_id": "UscrJg0kuDE",
            "title": "Transformers Prime Season 2 Episode 4 (3 of 3 Part) _Operation_ Bumblebee, Part 1_ in Hindi",
            "likes": "3242",
            "views": "326784",
            "thumbnail": "https://i.ytimg.com/vi/UscrJg0kuDE/mqdefault.jpg"
        },
        {
            "video_id": "Ty7_0MChGxc",
            "title": "Transformers Prime Season 2 Episode 5 (1 of 3 Part) _Operation_ Bumblebee, Part 2_ in Hindi",
            "likes": "3593",
            "views": "317625",
            "thumbnail": "https://i.ytimg.com/vi/Ty7_0MChGxc/mqdefault.jpg"
        },
        {
            "video_id": "VgeHBXBQhB4",
            "title": "Transformers Prime Season 2 Episode 5 (2 of 3 Part) _Operation_ Bumblebee, Part 2_ in Hindi",
            "likes": "2970",
            "views": "313098",
            "thumbnail": "https://i.ytimg.com/vi/VgeHBXBQhB4/mqdefault.jpg"
        },
        {
            "video_id": "YYw-gjA8T5s",
            "title": "Transformers Prime Season 2 Episode 5 (3 of 3 Part) _Operation_ Bumblebee, Part 2_ in Hindi",
            "likes": "3337",
            "views": "317967",
            "thumbnail": "https://i.ytimg.com/vi/YYw-gjA8T5s/mqdefault.jpg"
        },
        {
            "video_id": "5nERMu5mrWY",
            "title": "Transformers Prime Season 2 Episode 6 (1 of 3 Part) _Loose Cannons_ in Hindi",
            "likes": "3955",
            "views": "331516",
            "thumbnail": "https://i.ytimg.com/vi/5nERMu5mrWY/mqdefault.jpg"
        },
        {
            "video_id": "R24ke87BqMs",
            "title": "Transformers Prime Season 2 Episode 6 (2 of 3 Part) _Loose Cannons_ in Hindi",
            "likes": "3523",
            "views": "320068",
            "thumbnail": "https://i.ytimg.com/vi/R24ke87BqMs/mqdefault.jpg"
        },
        {
            "video_id": "cfy-HxdxFLk",
            "title": "Transformers Prime Season 2 Episode 6 (3 of 3 Part) _Loose Cannons_ in Hindi",
            "likes": "3854",
            "views": "326778",
            "thumbnail": "https://i.ytimg.com/vi/cfy-HxdxFLk/mqdefault.jpg"
        },
        {
            "video_id": "HZ70UKApmc4",
            "title": "Transformers Prime Season 2 Episode 7 (1 of 3 Part) _Crossfire_ in Hindi",
            "likes": "3247",
            "views": "300204",
            "thumbnail": "https://i.ytimg.com/vi/HZ70UKApmc4/mqdefault.jpg"
        },
        {
            "video_id": "fj9BpWI_k7Y",
            "title": "Transformers Prime Season 2 Episode 7 (2 of 3 Part) _Crossfire_ in Hindi",
            "likes": "3207",
            "views": "286085",
            "thumbnail": "https://i.ytimg.com/vi/fj9BpWI_k7Y/mqdefault.jpg"
        },
        {
            "video_id": "J0Zpfw0V_bk",
            "title": "Transformers Prime Season 2 Episode 7 (3 of 3 Part) _Crossfire_ in Hindi",
            "likes": "2691",
            "views": "308722",
            "thumbnail": "https://i.ytimg.com/vi/J0Zpfw0V_bk/mqdefault.jpg"
        },
        {
            "video_id": "2QF6bxVmBLI",
            "title": "Transformers Prime Season 2 Episode 8 (1 of 3 Part) _Nemesis Prime_ in Hindi",
            "likes": "2924",
            "views": "292779",
            "thumbnail": "https://i.ytimg.com/vi/2QF6bxVmBLI/mqdefault.jpg"
        },
        {
            "video_id": "TeWtrn49Z0U",
            "title": "Transformers Prime Season 2 Episode 8 (2 of 3 Part) _Nemesis Prime_ in Hindi",
            "likes": "3323",
            "views": "301657",
            "thumbnail": "https://i.ytimg.com/vi/TeWtrn49Z0U/mqdefault.jpg"
        },
        {
            "video_id": "OnqBXIWkgWo",
            "title": "Transformers Prime Season 2 Episode 8 (3 of 3 Part) _Nemesis Prime_ in Hindi",
            "likes": "3011",
            "views": "316600",
            "thumbnail": "https://i.ytimg.com/vi/OnqBXIWkgWo/mqdefault.jpg"
        },
        {
            "video_id": "1Ej7kFQ2l6Q",
            "title": "Transformers Prime Season 2 Episode 9 (1 of 3 Part) _Grill_ in Hindi",
            "likes": "3171",
            "views": "276393",
            "thumbnail": "https://i.ytimg.com/vi/1Ej7kFQ2l6Q/mqdefault.jpg"
        },
        {
            "video_id": "sXZp7BFpYig",
            "title": "Transformers Prime Season 2 Episode 9 (2 of 3 Part) _Grill_ in Hindi",
            "likes": "3011",
            "views": "264383",
            "thumbnail": "https://i.ytimg.com/vi/sXZp7BFpYig/mqdefault.jpg"
        },
        {
            "video_id": "jsD7ByVF42A",
            "title": "Transformers Prime Season 2 Episode 9 (3 of 3 Part) _Grill_ in Hindi",
            "likes": "3367",
            "views": "299788",
            "thumbnail": "https://i.ytimg.com/vi/jsD7ByVF42A/mqdefault.jpg"
        },
        {
            "video_id": "q-ec5zyXJY4",
            "title": "Transformers Prime Season 2 Episode 10 (1 of 3 Part) _Armada_ in Hindi",
            "likes": "2867",
            "views": "304834",
            "thumbnail": "https://i.ytimg.com/vi/q-ec5zyXJY4/mqdefault.jpg"
        },
        {
            "video_id": "Q2RbKldQbsQ",
            "title": "Transformers Prime Season 2 Episode 10 (2 of 3 Part) _Armada_ in Hindi",
            "likes": "2570",
            "views": "268698",
            "thumbnail": "https://i.ytimg.com/vi/Q2RbKldQbsQ/mqdefault.jpg"
        },
        {
            "video_id": "eR7rL5pcPcc",
            "title": "Transformers Prime Season 2 Episode 10 (3 of 3 Part) _Armada_ in Hindi",
            "likes": "2900",
            "views": "297645",
            "thumbnail": "https://i.ytimg.com/vi/eR7rL5pcPcc/mqdefault.jpg"
        },
        {
            "video_id": "8GcKjzLImcU",
            "title": "Transformers Prime Season 2 Episode 11 (1 of 3 Part) _Flying Mind_ in Hindi",
            "likes": "3010",
            "views": "292818",
            "thumbnail": "https://i.ytimg.com/vi/8GcKjzLImcU/mqdefault.jpg"
        },
        {
            "video_id": "JycpiFeoWDE",
            "title": "Transformers Prime Season 2 Episode 11 (2 of 3 Part) _Flying Mind_ in Hindi",
            "likes": "2867",
            "views": "282954",
            "thumbnail": "https://i.ytimg.com/vi/JycpiFeoWDE/mqdefault.jpg"
        },
        {
            "video_id": "DlSrXBEiLxA",
            "title": "Transformers Prime Season 2 Episode 11 (3 of 3 Part) _Flying Mind_ in Hindi",
            "likes": "2449",
            "views": "273274",
            "thumbnail": "https://i.ytimg.com/vi/DlSrXBEiLxA/mqdefault.jpg"
        },
        {
            "video_id": "gP6EGubUV38",
            "title": "Transformers Prime Season 2 Episode 12 (1 of 3 Part) _Tunnel Vision in Hindi",
            "likes": "3554",
            "views": "290716",
            "thumbnail": "https://i.ytimg.com/vi/gP6EGubUV38/mqdefault.jpg"
        },
        {
            "video_id": "2ZiB3aqb2T8",
            "title": "Transformers Prime Season 2 Episode 12 (2 of 3 Part) _Tunnel Vision in Hindi",
            "likes": "2363",
            "views": "248911",
            "thumbnail": "https://i.ytimg.com/vi/2ZiB3aqb2T8/mqdefault.jpg"
        },
        {
            "video_id": "KNEIlsHqtdE",
            "title": "Transformers Prime Season 2 Episode 12 (3 of 3 Part) _Tunnel Vision in Hindi",
            "likes": "2509",
            "views": "259142",
            "thumbnail": "https://i.ytimg.com/vi/KNEIlsHqtdE/mqdefault.jpg"
        },
        {
            "video_id": "6kMLJRMxPy4",
            "title": "Transformers Prime Season 2 Episode 13 (1 of 3 Part) _Triangulation_ in Hindi",
            "likes": "3007",
            "views": "261242",
            "thumbnail": "https://i.ytimg.com/vi/6kMLJRMxPy4/mqdefault.jpg"
        },
        {
            "video_id": "5xDt7-M9fmA",
            "title": "Transformers Prime Season 2 Episode 13 (2 of 3 Part) _Triangulation_ in Hindi",
            "likes": "2460",
            "views": "251957",
            "thumbnail": "https://i.ytimg.com/vi/5xDt7-M9fmA/mqdefault.jpg"
        },
        {
            "video_id": "Tv7c7nBhXVg",
            "title": "Transformers Prime Season 2 Episode 13 (3 of 3 Part) _Triangulation_ in Hindi",
            "likes": "2515",
            "views": "252222",
            "thumbnail": "https://i.ytimg.com/vi/Tv7c7nBhXVg/mqdefault.jpg"
        },
        {
            "video_id": "fOKQlW8-yHE",
            "title": "Transformers Prime Season 2 Episode 14 (1 of 3 Part)  Triage in Hindi",
            "likes": "2946",
            "views": "262725",
            "thumbnail": "https://i.ytimg.com/vi/fOKQlW8-yHE/mqdefault.jpg"
        },
        {
            "video_id": "AXssOK_Bp2M",
            "title": "Transformers Prime Season 2 Episode 14 (2 of 3 Part)  Triage  in Hindi",
            "likes": "2631",
            "views": "274412",
            "thumbnail": "https://i.ytimg.com/vi/AXssOK_Bp2M/mqdefault.jpg"
        },
        {
            "video_id": "sBQELn2qRv8",
            "title": "Transformers Prime Season 2 Episode 14 (3 of 3 Part)  Triage  in Hindi",
            "likes": "2659",
            "views": "272968",
            "thumbnail": "https://i.ytimg.com/vi/sBQELn2qRv8/mqdefault.jpg"
        },
        {
            "video_id": "WBUkIaVal2w",
            "title": "Transformers Prime Season 2 Episode 15 (1 of 3 Part)  _Toxicity_ in Hindi",
            "likes": "2806",
            "views": "264303",
            "thumbnail": "https://i.ytimg.com/vi/WBUkIaVal2w/mqdefault.jpg"
        },
        {
            "video_id": "CdB0VoQmGcY",
            "title": "Transformers Prime Season 2 Episode 15 (2 of 3 Part)  _Toxicity_ in Hindi",
            "likes": "2362",
            "views": "237573",
            "thumbnail": "https://i.ytimg.com/vi/CdB0VoQmGcY/mqdefault.jpg"
        },
        {
            "video_id": "0E9kEW306tQ",
            "title": "Transformers Prime Season 2 Episode 15 (3 of 3 Part) _Toxicity_ in Hindi",
            "likes": "2439",
            "views": "244457",
            "thumbnail": "https://i.ytimg.com/vi/0E9kEW306tQ/mqdefault.jpg"
        },
        {
            "video_id": "-jJlmu5vIn0",
            "title": "Transformers Prime Season 2 Episode 16 (1 of 3 Part) _Hurt_ in Hindi",
            "likes": "3221",
            "views": "263237",
            "thumbnail": "https://i.ytimg.com/vi/-jJlmu5vIn0/mqdefault.jpg"
        },
        {
            "video_id": "grafSWKbrh8",
            "title": "Transformers Prime Season 2 Episode 16 (2 of 3 Part) _Hurt_ in Hindi",
            "likes": "2865",
            "views": "262815",
            "thumbnail": "https://i.ytimg.com/vi/grafSWKbrh8/mqdefault.jpg"
        },
        {
            "video_id": "aaZ7DQHFw9Q",
            "title": "Transformers Prime Season 2 Episode 16 (3 of 3 Part) _Hurt_ in Hindi",
            "likes": "2669",
            "views": "289987",
            "thumbnail": "https://i.ytimg.com/vi/aaZ7DQHFw9Q/mqdefault.jpg"
        },
        {
            "video_id": "825JohzQzMg",
            "title": "Transformers Prime Season 2 Episode 17 (1 of 3 Part) _Out of the Past_ in Hindi",
            "likes": "3506",
            "views": "303062",
            "thumbnail": "https://i.ytimg.com/vi/825JohzQzMg/mqdefault.jpg"
        },
        {
            "video_id": "LEKpnNXKNbc",
            "title": "Transformers Prime Season 2 Episode 17 (2 of 3 Part) _Out of the Past_ in Hindi",
            "likes": "2699",
            "views": "261484",
            "thumbnail": "https://i.ytimg.com/vi/LEKpnNXKNbc/mqdefault.jpg"
        },
        {
            "video_id": "l6sIubSUw2Q",
            "title": "Transformers Prime Season 2 Episode 17 (3 of 3 Part) _Out of the Past_ in Hindi",
            "likes": "2657",
            "views": "259174",
            "thumbnail": "https://i.ytimg.com/vi/l6sIubSUw2Q/mqdefault.jpg"
        },
        {
            "video_id": "H9e2B2hY9a8",
            "title": "Transformers Prime Season 2 Episode 18 (1 of 3 Part) _New Recruit_ in Hindi",
            "likes": "4029",
            "views": "317055",
            "thumbnail": "https://i.ytimg.com/vi/H9e2B2hY9a8/mqdefault.jpg"
        },
        {
            "video_id": "T9e9enNoCYY",
            "title": "Transformers Prime Season 2 Episode 18 (2 of 3 Part) _New Recruit_ in Hindi",
            "likes": "3964",
            "views": "340114",
            "thumbnail": "https://i.ytimg.com/vi/T9e9enNoCYY/mqdefault.jpg"
        },
        {
            "video_id": "OYPJOtx4-jI",
            "title": "Transformers Prime Season 2 Episode 18 (3 of 3 Part) _New Recruit_ in Hindi",
            "likes": "3288",
            "views": "299691",
            "thumbnail": "https://i.ytimg.com/vi/OYPJOtx4-jI/mqdefault.jpg"
        },
        {
            "video_id": "LVCh-rQ2578",
            "title": "Transformers Prime Season 2 Episode 19 (1 of 3 Part) _The Human Factor_ in Hindi",
            "likes": "3329",
            "views": "299172",
            "thumbnail": "https://i.ytimg.com/vi/LVCh-rQ2578/mqdefault.jpg"
        },
        {
            "video_id": "fIC_2U87fn8",
            "title": "Transformers Prime Season 2 Episode 19 (2 of 3 Part) _The Human Factor_ in Hindi",
            "likes": "2960",
            "views": "288844",
            "thumbnail": "https://i.ytimg.com/vi/fIC_2U87fn8/mqdefault.jpg"
        },
        {
            "video_id": "vIsL9G_LI28",
            "title": "Transformers Prime Season 2 Episode 19 (3 of 3 Part) _The Human Factor_ in Hindi",
            "likes": "3168",
            "views": "286531",
            "thumbnail": "https://i.ytimg.com/vi/vIsL9G_LI28/mqdefault.jpg"
        },
        {
            "video_id": "09NU4wDR3IA",
            "title": "Transformers Prime Season 2 Episode 20 (1 of 3 Part) _Legacy_ in Hindi",
            "likes": "3672",
            "views": "317254",
            "thumbnail": "https://i.ytimg.com/vi/09NU4wDR3IA/mqdefault.jpg"
        },
        {
            "video_id": "6DhZMRhHbJw",
            "title": "Transformers Prime Season 2 Episode 20 (2 of 3 Part) _Legacy_ in Hindi",
            "likes": "3631",
            "views": "350352",
            "thumbnail": "https://i.ytimg.com/vi/6DhZMRhHbJw/mqdefault.jpg"
        },
        {
            "video_id": "2jCgyKvNc_k",
            "title": "Transformers Prime Season 2 Episode 20 (3 of 3 Part) _Legacy_ in Hindi",
            "likes": "6037",
            "views": "493896",
            "thumbnail": "https://i.ytimg.com/vi/2jCgyKvNc_k/mqdefault.jpg"
        },
        {
            "video_id": "jvpdje-1zMQ",
            "title": "Transformers Prime Season 2 Episode 21 (1 of 3 Part) _Alpha; Omega_ in Hindi",
            "likes": "4745",
            "views": "367193",
            "thumbnail": "https://i.ytimg.com/vi/jvpdje-1zMQ/mqdefault.jpg"
        },
        {
            "video_id": "wS79KxiBYx0",
            "title": "Transformers Prime Season 2 Episode 21 (2 of 3 Part) _Alpha; Omega_ in Hindi",
            "likes": "3862",
            "views": "352148",
            "thumbnail": "https://i.ytimg.com/vi/wS79KxiBYx0/mqdefault.jpg"
        },
        {
            "video_id": "Rsfnn_K3cGs",
            "title": "Transformers Prime Season 2 Episode 21 (3 of 3 Part) _Alpha; Omega_ in Hindi",
            "likes": "5877",
            "views": "531568",
            "thumbnail": "https://i.ytimg.com/vi/Rsfnn_K3cGs/mqdefault.jpg"
        },
        {
            "video_id": "TFJKb43U6MQ",
            "title": "Transformers Prime Season 2 Episode 22 (1 of 3 Part)_Hard Knocks_ in Hindi",
            "likes": "3461",
            "views": "303596",
            "thumbnail": "https://i.ytimg.com/vi/TFJKb43U6MQ/mqdefault.jpg"
        },
        {
            "video_id": "ykpMDTPP6rs",
            "title": "Transformers Prime Season 2 Episode 22 (2 of 3 Part)_Hard Knocks_ in Hindi",
            "likes": "3003",
            "views": "283243",
            "thumbnail": "https://i.ytimg.com/vi/ykpMDTPP6rs/mqdefault.jpg"
        },
        {
            "video_id": "meB-Kxx7Fx4",
            "title": "Transformers Prime Season 2 Episode 22 (3 of 3 Part)_Hard Knocks_ in Hindi",
            "likes": "3210",
            "views": "290978",
            "thumbnail": "https://i.ytimg.com/vi/meB-Kxx7Fx4/mqdefault.jpg"
        },
        {
            "video_id": "bWPfdASg-oI",
            "title": "Transformers Prime Season 2 Episode 23 (1 of 3 Part) _Inside Job_ in Hindi",
            "likes": "3081",
            "views": "277366",
            "thumbnail": "https://i.ytimg.com/vi/bWPfdASg-oI/mqdefault.jpg"
        },
        {
            "video_id": "oYSaKdtclXo",
            "title": "Transformers Prime Season 2 Episode 23 (2 of 3 Part) _Inside Job_ in Hindi",
            "likes": "2933",
            "views": "281176",
            "thumbnail": "https://i.ytimg.com/vi/oYSaKdtclXo/mqdefault.jpg"
        },
        {
            "video_id": "DdVfAJHkVjs",
            "title": "Transformers Prime Season 2 Episode 23 (3 of 3 Part) _Inside Job_ in Hindi",
            "likes": "3033",
            "views": "285262",
            "thumbnail": "https://i.ytimg.com/vi/DdVfAJHkVjs/mqdefault.jpg"
        },
        {
            "video_id": "HY0sOODo2jc",
            "title": "Transformers Prime Season 2 Episode 24 (1 of 3 Part) _Patch_ in Hindi",
            "likes": "3538",
            "views": "291771",
            "thumbnail": "https://i.ytimg.com/vi/HY0sOODo2jc/mqdefault.jpg"
        },
        {
            "video_id": "mR6ArLcBVeA",
            "title": "Transformers Prime Season 2 Episode 24 (2 of 3 Part) _Patch_ in Hindi",
            "likes": "3019",
            "views": "288187",
            "thumbnail": "https://i.ytimg.com/vi/mR6ArLcBVeA/mqdefault.jpg"
        },
        {
            "video_id": "80uWTQ55m7o",
            "title": "Transformers Prime Season 2 Episode 24 (3 of 3 Part) _Patch_ in Hindi",
            "likes": "3397",
            "views": "307371",
            "thumbnail": "https://i.ytimg.com/vi/80uWTQ55m7o/mqdefault.jpg"
        },
        {
            "video_id": "A0rqM0QOY_k",
            "title": "Transformers Prime Season 2 Episode 25 (1 of 3 Part) _Regeneration_ in Hindi",
            "likes": "4020",
            "views": "327360",
            "thumbnail": "https://i.ytimg.com/vi/A0rqM0QOY_k/mqdefault.jpg"
        },
        {
            "video_id": "bdqiWaXurTw",
            "title": "Transformers Prime Season 2 Episode 25 (2 of 3 Part) _Regeneration_ in Hindi",
            "likes": "4023",
            "views": "364160",
            "thumbnail": "https://i.ytimg.com/vi/bdqiWaXurTw/mqdefault.jpg"
        },
        {
            "video_id": "JJY1I8JKmrE",
            "title": "Transformers Prime Season 2 Episode 25 (3 of 3 Part) _Regeneration_ in Hindi",
            "likes": "3051",
            "views": "339347",
            "thumbnail": "https://i.ytimg.com/vi/JJY1I8JKmrE/mqdefault.jpg"
        },
        {
            "video_id": "61Y4T3fTYnw",
            "title": "Transformers Prime  Season  2 Episode 26 (1 of 3 Part) _Darkest Hour_ (Season 2 Final) in Hindi",
            "likes": "3078",
            "views": "313891",
            "thumbnail": "https://i.ytimg.com/vi/61Y4T3fTYnw/mqdefault.jpg"
        },
        {
            "video_id": "Ujthe9zXIbc",
            "title": "Transformers Prime  Season  2 Episode 26 (2 of 3 Part) _Darkest Hour_ (Season 2 Final) in Hindi",
            "likes": "3909",
            "views": "360213",
            "thumbnail": "https://i.ytimg.com/vi/Ujthe9zXIbc/mqdefault.jpg"
        },
        {
            "video_id": "xJO8FQK7rSE",
            "title": "Transformers Prime  Season  2 Episode 26 (3 of 3 Part) _Darkest Hour_ (Season 2 Final)  in Hindi",
            "likes": "3705",
            "views": "374185",
            "thumbnail": "https://i.ytimg.com/vi/xJO8FQK7rSE/mqdefault.jpg"
        },
        {
            "video_id": "u42FFZ-28VM",
            "title": "Transformers Prime Beast Hunters Season 3 Episode 1 (1 of 3 Part) _Darkmount Nevada_ in Hindi",
            "likes": "7029",
            "views": "675760",
            "thumbnail": "https://i.ytimg.com/vi/u42FFZ-28VM/mqdefault.jpg"
        },
        {
            "video_id": "CQEmeN-aw6M",
            "title": "Transformers Prime Beast Hunters Season 3 Episode 1 (2 of 3 Part) _Darkmount nevada_ in Hindi",
            "likes": "12476",
            "views": "1037020",
            "thumbnail": "https://i.ytimg.com/vi/CQEmeN-aw6M/mqdefault.jpg"
        },
        {
            "video_id": "J4u3qyK3apQ",
            "title": "Transformers Prime Beast Hunters Season 3 Episode 1 (3 of 3 Part) _Darkmount nevada_ in Hindi",
            "likes": "4709",
            "views": "525592",
            "thumbnail": "https://i.ytimg.com/vi/J4u3qyK3apQ/mqdefault.jpg"
        },
        {
            "video_id": "DnoMdB6JEAs",
            "title": "Transformers Prime Beast Hunters Season 3 Episode 2 (1 of 3 Part) _Scattered_ in Hindi",
            "likes": "5487",
            "views": "541023",
            "thumbnail": "https://i.ytimg.com/vi/DnoMdB6JEAs/mqdefault.jpg"
        },
        {
            "video_id": "33Y-wCz5SvU",
            "title": "Transformers Prime Beast Hunters Season 3 Episode 2 (2 of 3 Part) _Scattered_ in Hindi",
            "likes": "4688",
            "views": "490036",
            "thumbnail": "https://i.ytimg.com/vi/33Y-wCz5SvU/mqdefault.jpg"
        },
        {
            "video_id": "a85mFuaQFxs",
            "title": "Transformers Prime Beast Hunters Season 3 Episode 2 (3 of 3 Part) _Scattered_ in Hindi",
            "likes": "4853",
            "views": "544893",
            "thumbnail": "https://i.ytimg.com/vi/a85mFuaQFxs/mqdefault.jpg"
        },
        {
            "video_id": "ZGok4-5GopE",
            "title": "Transformers Prime Beast Hunters Season 3 Episode 3 (1 of 3 Part) _Prey_ in Hindi",
            "likes": "5171",
            "views": "528967",
            "thumbnail": "https://i.ytimg.com/vi/ZGok4-5GopE/mqdefault.jpg"
        },
        {
            "video_id": "x5XN77EkJMI",
            "title": "Transformers Prime Beast Hunters Season 3 Episode 3 (2 of 3 Part) _Prey_ in Hindi",
            "likes": "4050",
            "views": "511095",
            "thumbnail": "https://i.ytimg.com/vi/x5XN77EkJMI/mqdefault.jpg"
        },
        {
            "video_id": "O3PSesLC928",
            "title": "Transformers Prime Beast Hunters Season 3 Episode 3 (3 of 3 Part) _Prey_ in Hindi",
            "likes": "5605",
            "views": "532319",
            "thumbnail": "https://i.ytimg.com/vi/O3PSesLC928/mqdefault.jpg"
        },
        {
            "video_id": "r2bKHmOthZ4",
            "title": "Transformers Prime Beast Hunters Season 3 Episode 4 (1 of 3 Part) _Rebellion_ in Hindi",
            "likes": "5498",
            "views": "599446",
            "thumbnail": "https://i.ytimg.com/vi/r2bKHmOthZ4/mqdefault.jpg"
        },
        {
            "video_id": "q9ZXmyetIHE",
            "title": "Transformers Prime Beast Hunters Season 3 Episode 4 (2 of 3 Part) _Rebellion_ in Hindi",
            "likes": "6158",
            "views": "673720",
            "thumbnail": "https://i.ytimg.com/vi/q9ZXmyetIHE/mqdefault.jpg"
        },
        {
            "video_id": "hGU50QaRzTY",
            "title": "Transformers Prime Beast Hunters Season 3 Episode 4 (3 of 3 Part) _Rebellion_ in Hindi",
            "likes": "7325",
            "views": "676412",
            "thumbnail": "https://i.ytimg.com/vi/hGU50QaRzTY/mqdefault.jpg"
        },
        {
            "video_id": "cYQC86cF7Ms",
            "title": "Transformers Prime Beast Hunters Season 3 Episode 5 (1 of 3 Part) _Project Predacon_ in Hindi",
            "likes": "5784",
            "views": "574173",
            "thumbnail": "https://i.ytimg.com/vi/cYQC86cF7Ms/mqdefault.jpg"
        },
        {
            "video_id": "rBcpeWgT_9U",
            "title": "Transformers Prime Beast Hunters Season 3 Episode 5 (2 of 3 Part) _Project Predacon_ in Hindi",
            "likes": "5786",
            "views": "501947",
            "thumbnail": "https://i.ytimg.com/vi/rBcpeWgT_9U/mqdefault.jpg"
        },
        {
            "video_id": "uDLxJpjE-Sw",
            "title": "Transformers Prime Beast Hunters Season 3 Episode 5 (3 of 3 Part) _Project Predacon_ in Hindi",
            "likes": "3940",
            "views": "473157",
            "thumbnail": "https://i.ytimg.com/vi/uDLxJpjE-Sw/mqdefault.jpg"
        },
        {
            "video_id": "yK7EoGSp84w",
            "title": "Transformers Prime Beast Hunters Season 3 Episode 6 (1 of 3 Part) _Chain of Command_ in Hindi",
            "likes": "4744",
            "views": "451217",
            "thumbnail": "https://i.ytimg.com/vi/yK7EoGSp84w/mqdefault.jpg"
        },
        {
            "video_id": "D8_2lzKfqC0",
            "title": "Transformers Prime Beast Hunters Season 3 Episode 6 (2 of 3 Part) _Chain of Command_ in Hindi",
            "likes": "4185",
            "views": "429829",
            "thumbnail": "https://i.ytimg.com/vi/D8_2lzKfqC0/mqdefault.jpg"
        },
        {
            "video_id": "dx2_37jCUdE",
            "title": "Transformers Prime Beast Hunters Season 3 Episode 6 (3 of 3 Part) _Chain of Command_ in Hindi",
            "likes": "4115",
            "views": "439301",
            "thumbnail": "https://i.ytimg.com/vi/dx2_37jCUdE/mqdefault.jpg"
        },
        {
            "video_id": "WEEOZccP9EY",
            "title": "Transformers Prime Beast Hunters Season 3 Episode 7 (1 of 3 Part) _Plus One_ in Hindi",
            "likes": "5250",
            "views": "439807",
            "thumbnail": "https://i.ytimg.com/vi/WEEOZccP9EY/mqdefault.jpg"
        },
        {
            "video_id": "UWjy5UYIxzc",
            "title": "Transformers Prime Beast Hunters Season 3 Episode 7 (2 of 3 Part) _Plus One_ in Hindi",
            "likes": "4034",
            "views": "402269",
            "thumbnail": "https://i.ytimg.com/vi/UWjy5UYIxzc/mqdefault.jpg"
        },
        {
            "video_id": "6WNx0tn3TY4",
            "title": "Transformers Prime Beast Hunters Season 3 Episode 7 (3 of 3 Part) _Plus One_ in Hindi",
            "likes": "3898",
            "views": "396944",
            "thumbnail": "https://i.ytimg.com/vi/6WNx0tn3TY4/mqdefault.jpg"
        },
        {
            "video_id": "gFqPmBqhP0k",
            "title": "Transformers Prime Beast Hunters Season 3 Episode 8 (1 of 3 Part) _Thirst_  in Hindi",
            "likes": "5484",
            "views": "444494",
            "thumbnail": "https://i.ytimg.com/vi/gFqPmBqhP0k/mqdefault.jpg"
        },
        {
            "video_id": "R7sUE_2159s",
            "title": "Transformers Prime Beast Hunters Season 3 Episode 8 (2 of 3 Part) _Thirst_  in Hindi",
            "likes": "4526",
            "views": "426855",
            "thumbnail": "https://i.ytimg.com/vi/R7sUE_2159s/mqdefault.jpg"
        },
        {
            "video_id": "pG-3yLr5nw0",
            "title": "Transformers Prime Beast Hunters Season 3 Episode 8 (3 of 3 Part) _Thirst_  in Hindi",
            "likes": "5201",
            "views": "455784",
            "thumbnail": "https://i.ytimg.com/vi/pG-3yLr5nw0/mqdefault.jpg"
        },
        {
            "video_id": "DfA5wuA5F28",
            "title": "Transformers Prime Beast Hunters Season 3 Episode 9 (1 of 3 Part) _Evolution_ in Hindi",
            "likes": "5245",
            "views": "450084",
            "thumbnail": "https://i.ytimg.com/vi/DfA5wuA5F28/mqdefault.jpg"
        },
        {
            "video_id": "wGkIGqNRHQQ",
            "title": "Transformers Prime Beast Hunters Season 3 Episode 9 (2 of 3 Part) _Evolution_ in Hindi",
            "likes": "4914",
            "views": "448235",
            "thumbnail": "https://i.ytimg.com/vi/wGkIGqNRHQQ/mqdefault.jpg"
        },
        {
            "video_id": "BM5Vlff3tJE",
            "title": "Transformers Prime Beast Hunters Season 3 Episode 9 (3 of 3 Part) _Evolution_ in Hindi",
            "likes": "4423",
            "views": "448608",
            "thumbnail": "https://i.ytimg.com/vi/BM5Vlff3tJE/mqdefault.jpg"
        },
        {
            "video_id": "6XbeXJptloo",
            "title": "Transformers Prime Beast Hunters Season 3 Episode 10 (1 of 3 Part) _Minus One_ in Hindi",
            "likes": "5003",
            "views": "432860",
            "thumbnail": "https://i.ytimg.com/vi/6XbeXJptloo/mqdefault.jpg"
        },
        {
            "video_id": "PY1fNa8MGhc",
            "title": "Transformers Prime Beast Hunters Season 3 Episode 10 (2 of 3 Part) _Minus One_ in Hindi",
            "likes": "4342",
            "views": "425624",
            "thumbnail": "https://i.ytimg.com/vi/PY1fNa8MGhc/mqdefault.jpg"
        },
        {
            "video_id": "COVuEnLLqhQ",
            "title": "Transformers Prime Beast Hunters Season 3 Episode 10 (3 of 3 Part) _Minus One_ in Hindi",
            "likes": "4099",
            "views": "411254",
            "thumbnail": "https://i.ytimg.com/vi/COVuEnLLqhQ/mqdefault.jpg"
        },
        {
            "video_id": "0Lr2KIiJYco",
            "title": "Transformers Prime Beast Hunters Season 3 Episode 11 (1 of 3 part) _Persuasion_ in Hindi",
            "likes": "4392",
            "views": "400013",
            "thumbnail": "https://i.ytimg.com/vi/0Lr2KIiJYco/mqdefault.jpg"
        },
        {
            "video_id": "kx6cSF4MRlY",
            "title": "Transformers Prime Beast Hunters Season 3 Episode 11 (2 of 3 part) _Persuasion_ in Hindi",
            "likes": "4768",
            "views": "405736",
            "thumbnail": "https://i.ytimg.com/vi/kx6cSF4MRlY/mqdefault.jpg"
        },
        {
            "video_id": "aESGoJovKZE",
            "title": "Transformers Prime Beast Hunters Season 3 Episode 11 (3 of 3 part) _Persuasion_ in Hindi",
            "likes": "5097",
            "views": "409094",
            "thumbnail": "https://i.ytimg.com/vi/aESGoJovKZE/mqdefault.jpg"
        },
        {
            "video_id": "K8gIPcA-eeo",
            "title": "Transformers Prime Beast Hunters Season 3 Episode 12 (1 of 3 Part) _Synthesis_ in Hindi",
            "likes": "4502",
            "views": "402740",
            "thumbnail": "https://i.ytimg.com/vi/K8gIPcA-eeo/mqdefault.jpg"
        },
        {
            "video_id": "7_RVsUEeJ8Q",
            "title": "Transformers Prime Beast Hunters Season 3 Episode 12 (2 of 3 Part) _Synthesis_ in Hindi",
            "likes": "4367",
            "views": "427827",
            "thumbnail": "https://i.ytimg.com/vi/7_RVsUEeJ8Q/mqdefault.jpg"
        },
        {
            "video_id": "taIdcYpMjh0",
            "title": "Transformers Prime Beast Hunters Season 3 Episode 12 (3 of 3 Part) _Synthesis_ in Hindi",
            "likes": "5480",
            "views": "461206",
            "thumbnail": "https://i.ytimg.com/vi/taIdcYpMjh0/mqdefault.jpg"
        },
        {
            "video_id": "loZKtCjkmMw",
            "title": "Transformers Prime Beast Hunters Season 3 Episode 13 (1 of 3 Part)_Deadlock_ (Last Episode) in Hindi",
            "likes": "5885",
            "views": "562068",
            "thumbnail": "https://i.ytimg.com/vi/loZKtCjkmMw/mqdefault.jpg"
        },
        {
            "video_id": "bkUf11tYTJk",
            "title": "Transformers Prime Beast Hunters Season 3 Episode 13 (2 of 3 Part)_Deadlock_ (Last Episode) in Hindi",
            "likes": "6775",
            "views": "598060",
            "thumbnail": "https://i.ytimg.com/vi/bkUf11tYTJk/mqdefault.jpg"
        },
        {
            "video_id": "choeplTO7j0",
            "title": "Transformers Prime Beast Hunters Season 3 Episode 13 (3 of 3 Part)_Deadlock_ (Last Episode) in Hindi",
            "likes": "8053",
            "views": "615238",
            "thumbnail": "https://i.ytimg.com/vi/choeplTO7j0/mqdefault.jpg"
        },
        {
            "video_id": "haTJm9NDneg",
            "title": "Transformers Prime Beast Hunters_ Predacons Rising_ Movie (1 of 12 Part) in Hindi",
            "likes": "7158",
            "views": "567076",
            "thumbnail": "https://i.ytimg.com/vi/haTJm9NDneg/mqdefault.jpg"
        },
        {
            "video_id": "MmlYxx8uIN8",
            "title": "Transformers Prime Beast Hunters_ Predacons Rising_ Movie (2 of 12 Part) in Hindi",
            "likes": "5405",
            "views": "477455",
            "thumbnail": "https://i.ytimg.com/vi/MmlYxx8uIN8/mqdefault.jpg"
        },
        {
            "video_id": "MocK9GMgaWo",
            "title": "Transformers Prime Beast Hunters_ Predacons Rising_ Movie (3 of 12 Part) in Hindi",
            "likes": "4191",
            "views": "447904",
            "thumbnail": "https://i.ytimg.com/vi/MocK9GMgaWo/mqdefault.jpg"
        },
        {
            "video_id": "7gzaTXi3dLA",
            "title": "Transformers Prime Beast Hunters_ Predacons Rising_ Movie (4 of 12 Part) in Hindi",
            "likes": "4476",
            "views": "439808",
            "thumbnail": "https://i.ytimg.com/vi/7gzaTXi3dLA/mqdefault.jpg"
        },
        {
            "video_id": "NV8I_wvSdQ0",
            "title": "Transformers Prime Beast Hunters_ Predacons Rising_ Movie (5 of 12 Part) in Hindi",
            "likes": "4138",
            "views": "437861",
            "thumbnail": "https://i.ytimg.com/vi/NV8I_wvSdQ0/mqdefault.jpg"
        },
        {
            "video_id": "tQX3rsKzHU0",
            "title": "Transformers Prime Beast Hunters_ Predacons Rising_ Movie (6 of 12 Part) in Hindi",
            "likes": "4788",
            "views": "424507",
            "thumbnail": "https://i.ytimg.com/vi/tQX3rsKzHU0/mqdefault.jpg"
        },
        {
            "video_id": "b_lWpEt_IZQ",
            "title": "Transformers Prime Beast Hunters_ Predacons Rising_ Movie (7 of 12 Part) in Hindi",
            "likes": "4401",
            "views": "414629",
            "thumbnail": "https://i.ytimg.com/vi/b_lWpEt_IZQ/mqdefault.jpg"
        },
        {
            "video_id": "Oihmd41mVwQ",
            "title": "Transformers Prime Beast Hunters_ Predacons Rising_ Movie (8 of 12 Part) in Hindi",
            "likes": "4186",
            "views": "409427",
            "thumbnail": "https://i.ytimg.com/vi/Oihmd41mVwQ/mqdefault.jpg"
        },
        {
            "video_id": "ZkObyj63Nls",
            "title": "Transformers Prime Beast Hunters_ Predacons Rising_ Movie (9 of 12 Part) in Hindi",
            "likes": "4290",
            "views": "416480",
            "thumbnail": "https://i.ytimg.com/vi/ZkObyj63Nls/mqdefault.jpg"
        },
        {
            "video_id": "FnU0mVpr_IE",
            "title": "Transformers Prime Beast Hunters_ Predacons Rising_ Movie (10 of 12 Part) in Hindi",
            "likes": "4412",
            "views": "444840",
            "thumbnail": "https://i.ytimg.com/vi/FnU0mVpr_IE/mqdefault.jpg"
        },
        {
            "video_id": "gAlEzZ8jY-s",
            "title": "Transformers Prime Beast Hunters _Predacons Rising_ Movie (11 of 12 Part) in Hindi",
            "likes": "4250",
            "views": "458217",
            "thumbnail": "https://i.ytimg.com/vi/gAlEzZ8jY-s/mqdefault.jpg"
        },
        {
            "video_id": "yjzK35AyPU4",
            "title": "Transformers Prime Beast Hunters_ Predacons Rising_ Movie (12 of 12 Part) in Hindi",
            "likes": "11665",
            "views": "595227",
            "thumbnail": "https://i.ytimg.com/vi/yjzK35AyPU4/mqdefault.jpg"
        }
    ]
}
